Workbook

Sheet Dashboard
A1: MD MARBLE — FACTORY CONTROL DASHBOARD
A2: MD Finishes • Triq ix-Xwieni, Alberttown, Marsa • VAT MT26862103 • live overview (figures update automatically)
B4: KEY NUMBERS
B5: INVOICED & DELIVERED (incl VAT) | E5: PIPELINE — QUOTES AWAITING CONFIRM
B6: =SUMIF('Orders & Payments'!$G$3:$G$200,"Invoice",'Orders & Payments'!$N$3:$N$200)+SUMIF('Orders & Payments'!$G$3:$G$200,"Delivery-Invoice",'Orders & Payments'!$N$3:$N$200) -> 139259.89 | E6: =SUMIF('Orders & Payments'!$G$3:$G$200,"Quotation",'Orders & Payments'!$N$3:$N$200) -> 286888.31
B8: TOTAL RECEIVED / DEPOSITS | E8: OUTSTANDING TO COLLECT
B9: =SUM('Orders & Payments'!$O$3:$O$200) -> 12372.58 | E9: =SUMIF('Orders & Payments'!$G$3:$G$200,"Invoice",'Orders & Payments'!$P$3:$P$200)+SUMIF('Orders & Payments'!$G$3:$G$200,"Delivery-Invoice",'Orders & Payments'!$P$3:$P$200) -> 126887.31
B11: JOBS / DOCUMENTS LOGGED | E11: QUOTES AWAITING CONFIRMATION
B12: =COUNTA('Orders & Payments'!$A$3:$A$200) -> 86 | E12: =COUNTIF('Orders & Payments'!$G$3:$G$200,"Quotation") -> 35
B15: BY DOCUMENT TYPE | E15: BY WORK TYPE
B16: Type | C16: Count | D16: Value (incl VAT) | E16: Type | F16: Count | G16: Value (incl VAT)
B17: Quotation | C17: =COUNTIF('Orders & Payments'!$G$3:$G$200,"Quotation") -> 35 | D17: =SUMIF('Orders & Payments'!$G$3:$G$200,"Quotation",'Orders & Payments'!$N$3:$N$200) -> 286888.31 | E17: Supply Only | F17: =COUNTIF('Orders & Payments'!$J$3:$J$200,"Supply Only") -> 38 | G17: =SUMIF('Orders & Payments'!$J$3:$J$200,"Supply Only",'Orders & Payments'!$N$3:$N$200) -> 167223.71
B18: Invoice | C18: =COUNTIF('Orders & Payments'!$G$3:$G$200,"Invoice") -> 22 | D18: =SUMIF('Orders & Payments'!$G$3:$G$200,"Invoice",'Orders & Payments'!$N$3:$N$200) -> 49686.05 | E18: Supply & Install | F18: =COUNTIF('Orders & Payments'!$J$3:$J$200,"Supply & Install") -> 42 | G18: =SUMIF('Orders & Payments'!$J$3:$J$200,"Supply & Install",'Orders & Payments'!$N$3:$N$200) -> 244234.29
B19: Delivery-Invoice | C19: =COUNTIF('Orders & Payments'!$G$3:$G$200,"Delivery-Invoice") -> 28 | D19: =SUMIF('Orders & Payments'!$G$3:$G$200,"Delivery-Invoice",'Orders & Payments'!$N$3:$N$200) -> 89573.84 | E19: Service | F19: =COUNTIF('Orders & Payments'!$J$3:$J$200,"Service") -> 6 | G19: =SUMIF('Orders & Payments'!$J$3:$J$200,"Service",'Orders & Payments'!$N$3:$N$200) -> 24690.2
B20: Credit Note | C20: =COUNTIF('Orders & Payments'!$G$3:$G$200,"Credit Note") -> 1 | D20: =SUMIF('Orders & Payments'!$G$3:$G$200,"Credit Note",'Orders & Payments'!$N$3:$N$200) -> 10000
B22: How to use: fill the yellow cells. Everything else (Pending, Dashboard, Client totals) calculates by itself. Tabs are grouped: bronze = overview, blue = sales/orders, green = factory & people.

Sheet Orders & Payments
A1: ORDERS, DELIVERIES & PAYMENTS
A2: Order ID | B2: Date | C2: Client | D2: Site / Location | E2: Description of Works | F2: Material | G2: Doc Type | H2: Quote No. | I2: Invoice No. | J2: Work Type | K2: Confirmed? | L2: Amount excl VAT | M2: VAT | N2: Total incl VAT | O2: Deposit / Paid | P2: Pending | Q2: Payment Due When | R2: Payment Status | S2: Lead Time (days) | T2: Delivery / Install Date | U2: Notes
A3: MD-001 | B3: 45625 | C3: Luqa New Airport | D3: Luqa Airport | E3: Supply & Install of Biege Lime Stone (31.2 sqm) + installation 93 lm, plus extra door sills & leveling labour | F3: Biege Lime Stone | G3: Quotation | H3: 175 | J3: Supply & Install | K3: No | L3: 6603.32 | M3: 1188.6 | N3: 7791.92 | O3: 0 | P3: =N3-O3 -> 7791.92 | Q3: Deposit on Confirmation | R3: Awaiting Confirmation | U3: Old quote (Nov-2024) — confirm if still live or already done. Filename hint: Satariano / Luqa.
A4: MD-002 | B4: 45868 | C4: Qrendi (site) | D4: Qrendi | E4: Supply of marble — limestone 90×60 brushed (10.8 + 2.16 m²), travertine 40×60 unfilled 12 sqm, 240×240 slab | F4: Limestone / Travertine | G4: Quotation | H4: 229 | J4: Supply Only | K4: No | L4: =756+151+340+372 -> 1619 | M4: 291.42 | N4: 1910.42 | O4: 0 | P4: =N4-O4 -> 1910.42 | Q4: Deposit on Confirmation | R4: Awaiting Confirmation | U4: No company name / VAT on doc — confirm client identity.
A5: MD-003 | B5: 45905 | C5: WE MALTA LTD | D5: Pieta | E5: Supply & deliver of Biege stone for lifts — Pieta site | F5: Biege Stone | G5: Invoice | H5: 390 | I5: 400186 | J5: Supply Only | K5: Yes | L5: 1380 | M5: 248.4 | N5: 1628.4 | O5: 0 | P5: =N5-O5 -> 1628.4 | Q5: On Delivery | R5: Pending | U5: VAT 26150532, Birkirkara. Lift cladding supply.
A6: MD-004 | B6: 45917 | C6: Marsa – Hand-Crafted Job | D6: Marsa | E6: Supply & install of hand-crafted marble designs, full bullnose edging & on-site polish | F6: Marble (hand-crafted) | G6: Quotation | H6: 239 | J6: Supply & Install | K6: No | L6: 3770 | M6: 678.6 | N6: 4448.6 | O6: 0 | P6: =N6-O6 -> 4448.6 | Q6: Deposit on Confirmation | R6: Awaiting Confirmation | U6: Doc shows customer: "MARSA" (no VAT). Confirm contact.
A7: MD-005 | B7: 45918 | C7: AX CONSTRUCTION LIMITED | D7: Airport / Mosta | E7: Supply of Biege Limestone | F7: Biege Limestone | G7: Delivery-Invoice | I7: 1000236 | J7: Supply Only | K7: Yes | L7: 225 | M7: 40.5 | N7: 265.5 | O7: 0 | P7: =N7-O7 -> 265.5 | Q7: On Delivery | R7: Pending | U7: VAT 12949330, Triq id-Difiza Civili, Mosta.
A8: MD-006 | B8: 45923 | C8: Amanda | D8: Buggiba | E8: Supply of granite (cut to ~22 sizes) — Buggiba site | F8: Granite | G8: Delivery-Invoice | I8: 1000238 | J8: Supply Only | K8: Yes | L8: 282 | M8: 50.76 | N8: 332.76 | O8: 0 | P8: =N8-O8 -> 332.76 | Q8: On Delivery | R8: Pending | U8: Doc shows "AMANDA" (no VAT). Many cut pieces listed.
A9: MD-007 | B9: 45926 | C9: 1909 INVESTMENTS LTD | D9: Zebbug | E9: CREDIT NOTE against invoice 400190 — Supply & Install Travertine Sills & Stairs | F9: Travertine | G9: Credit Note | H9: 29 | I9: (ref 400190) | J9: Supply & Install | K9: N/A | L9: 8474.58 | M9: 1525.42 | N9: 10000 | O9: 0 | P9: =N9-O9 -> 10000 | Q9: See Notes | R9: Credit Note | U9: Credit note offsets Invoice 400190 (not uploaded). VAT 20541622.
A10: MD-008 | B10: 45926 | C10: 1909 INVESTMENTS LTD | D10: Zebbug | E10: Supply & Install of Travertine Sills & Stairs | F10: Travertine | G10: Invoice | H10: 390 | I10: 400191 | J10: Supply & Install | K10: Yes | L10: 8898.31 | M10: 1601.7 | N10: 10500.01 | O10: 0 | P10: =N10-O10 -> 10500.01 | Q10: On Completion | R10: Pending | U10: VAT 20541622, BG House No.3, Zebbug.
A11: MD-009 | B11: 45929 | C11: SUNSPOTS LTD | D11: Pieta | E11: Supply of Biege Travertine 40×60 + Galala sills & stairs — Pieta site | F11: Travertine & Galala | G11: Invoice | H11: 390 | I11: 400192 | J11: Supply Only | K11: Yes | L11: 3000 | M11: 540 | N11: 3540 | O11: 0 | P11: =N11-O11 -> 3540 | Q11: On Delivery | R11: Pending | U11: VAT 12527802, St Julians.
A12: MD-010 | B12: 45931 | C12: ROGER SATARIANO & SON LTD | D12: Mriehel | E12: Supply & Install of Lava Black marble for stairs & façade (31.6 sqm) — Mriehel site | F12: Lava Black | G12: Quotation | H12: 243 | J12: Supply & Install | K12: No | L12: 4330 | M12: 779.4 | N12: 5109.4 | O12: 0 | P12: =N12-O12 -> 5109.4 | Q12: Deposit on Confirmation | R12: Awaiting Confirmation | U12: VAT 1055-2337, 122 Msida Valley Rd, Birkirkara.
A13: MD-011 | B13: 45936 | C13: ICI LIMITED | D13: Birkirkara | E13: Supply of Travertine incl material + cutting + round edges (9.2 sqm) | F13: Travertine | G13: Invoice | H13: 390 | I13: 400193 | J13: Supply Only | K13: Yes | L13: 690 | M13: 124.2 | N13: 814.2 | O13: 0 | P13: =N13-O13 -> 814.2 | Q13: On Delivery | R13: Pending | U13: VAT MT17813220, Triq l-Artigjanat Zone 4, Birkirkara.
A14: MD-012 | B14: 45959 | C14: ICI LIMITED | D14: Villa Fiorini | E14: Villa Fiorini — remove & replace marble sills + install | F14: Marble (sills) | G14: Quotation | H14: 259 | J14: Supply & Install | K14: No | L14: 480 | M14: 86.4 | N14: 566.4 | O14: 0 | P14: =N14-O14 -> 566.4 | Q14: Deposit on Confirmation | R14: Awaiting Confirmation | U14: Same client as MD-011/MD-018 (ICI Ltd).
A15: MD-013 | B15: 45959 | C15: Jhon Soler | D15: 15 Howard St, Sliema | E15: Supply & Install of 7 lifts cladding + delivery & unloading to each floor | F15: Marble cladding | G15: Quotation | H15: 258 | J15: Supply & Install | K15: No | L15: =2170+150 -> 2320 | M15: 417.6 | N15: 2737.6 | O15: 0 | P15: =N15-O15 -> 2737.6 | Q15: Deposit on Confirmation | R15: Awaiting Confirmation | U15: Doc shows "Jhon Soler", Sliema (no VAT).
A16: MD-014 | B16: 45965 | C16: 1909 INVESTMENTS LTD | D16: Zebbug — Flats 1–12 | E16: Supply & Install of Travertine — covers Flats 1,2,3,4,5,6,7,8,9,10,11 & 12 | F16: Travertine | G16: Delivery-Invoice | I16: 1000252 | J16: Supply & Install | K16: Yes | L16: 5554 | M16: 999.72 | N16: 6553.72 | O16: 0 | P16: =N16-O16 -> 6553.72 | Q16: On Completion | R16: Pending | U16: VAT 20541622. Supply 3,154 + Install 2,400.
A17: MD-015 | B17: 45965 | C17: Robert (RMX Ltd) | D17: Marsa | E17: Supply + delivery of Silvia Marble | F17: Silvia Marble | G17: Delivery-Invoice | I17: 1000253 | J17: Supply Only | K17: Yes | L17: 2300 | M17: 414 | N17: 2714 | O17: 0 | P17: =N17-O17 -> 2714 | Q17: On Delivery | R17: Pending | U17: Doc shows "MARSA"; filename hint: Robert / RMX Ltd. Confirm.
A18: MD-016 | B18: 45965 | C18: ROGER SATARIANO & SON LTD | D18: Mriehel | E18: Supply & Install of Lava aluminium door sills (extra) — Mriehel site | F18: Lava | G18: Delivery-Invoice | I18: 1000254 | J18: Supply & Install | K18: Yes | L18: 265 | M18: 47.7 | N18: 312.7 | O18: 0 | P18: =N18-O18 -> 312.7 | Q18: On Completion | R18: Pending | U18: VAT 1055-2337. Extra to the Mriehel Lava Black job (MD-010).
A19: MD-017 | B19: 45966 | C19: PROJECT TECHNIK LTD | D19: Qormi | E19: Supply of Trista Grey (27 sqm) | F19: Trista Grey | G19: Delivery-Invoice | I19: 1000255 | J19: Supply Only | K19: Yes | L19: 1485 | M19: 267.3 | N19: 1752.3 | O19: 0 | P19: =N19-O19 -> 1752.3 | Q19: On Delivery | R19: Pending | U19: VAT MT19667814, Cannon Road, Qormi.
A20: MD-018 | B20: 45966 | C20: ICI LIMITED | D20: Sliema (Gafar) | E20: Touch up & paint — Gafar at Sliema | F20: Touch-up / paint | G20: Invoice | H20: 390 | I20: 400195 | J20: Service | K20: Yes | L20: 800 | M20: 144 | N20: 944 | O20: 0 | P20: =N20-O20 -> 944 | Q20: See Notes | R20: Pending | U20: Agreed split per doc: €660.80 cash + €283.20 barter (= €944).
A21: MD-019 | B21: 45967 | C21: Lee | D21: Siggiewi / Marsa | E21: Supply of Biege Travertine sills (11 cut sizes) + delivery | F21: Biege Travertine | G21: Delivery-Invoice | I21: 1000256 | J21: Supply Only | K21: Yes | L21: 370 | M21: 66.6 | N21: 436.6 | O21: 0 | P21: =N21-O21 -> 436.6 | Q21: On Delivery | R21: Pending | U21: Doc shows "Lee", Marsa; filename hint: Siggiewi.
A22: MD-020 | B22: 45975 | C22: STEPHEN FARRUGIA | D22: Santa Venera | E22: Supply & Install of Marble — BALANCE on Quote 227 (project total €13,806 incl VAT; deposit €5,522.40 already paid on Inv 400181) | F22: Marble | G22: Delivery-Invoice | H22: 227 | I22: 1000258 | J22: Supply & Install | K22: Yes | L22: 7020 | M22: 1263.6 | N22: 8283.6 | O22: 0 | P22: =N22-O22 -> 8283.6 | Q22: On Completion | R22: Pending | U22: VAT mt13709420. This row = remaining balance €8,283.60. Deposit already collected via Inv 400181. Fiscal Invoice 400196 (14/11/2025) was issued for this same balance — same sale, counted once here.
A23: MD-021 | B23: 45973 | C23: Christian Fenech | D23: Msida | E23: Supply of Biege stone sills (24 lm) | F23: Biege stone | G23: Delivery-Invoice | I23: 1000257 | J23: Supply Only | K23: Yes | L23: 384 | M23: 69.12 | N23: 453.12 | O23: 0 | P23: =N23-O23 -> 453.12 | Q23: On Delivery | R23: Pending | U23: VAT 1690-8714, Msida.
A24: MD-022 | B24: 45976 | C24: Dario | D24: Marsa | E24: Supply of kitchen top — Quartz Gold (OPTION A) | F24: Quartz Gold | G24: Quotation | H24: 264 | J24: Supply Only | K24: No | L24: 3400 | M24: 612 | N24: 4012 | O24: 0 | P24: =N24-O24 -> 4012 | Q24: Deposit on Confirmation | R24: Awaiting Confirmation | U24: OPTION A for Dario kitchen. Alternative to Q265 (Calacatta) — client picks ONE. No VAT on doc.
A25: MD-023 | B25: 45976 | C25: Dario | D25: Marsa | E25: Supply of kitchen top — Quartz Calacatta Gold (OPTION B) | F25: Quartz Calacatta Gold | G25: Quotation | H25: 265 | J25: Supply Only | K25: No | L25: 3025 | M25: 544.5 | N25: 3569.5 | O25: 0 | P25: =N25-O25 -> 3569.5 | Q25: Deposit on Confirmation | R25: Awaiting Confirmation | U25: OPTION B for Dario kitchen. Alternative to Q264 (Quartz Gold) — client picks ONE. No VAT on doc.
A26: MD-024 | B26: 45978 | C26: BURMARRAD GROUP PROPERTIES LIMITED | D26: Marsa | E26: Plastering & painting finishings — clean ceiling, treat & apply Sika, plaster & paint | F26: Plaster / paint | G26: Invoice | I26: 5000140 | J26: Service | K26: Yes | L26: 1500 | M26: 270 | N26: 1770 | O26: 0 | P26: =N26-O26 -> 1770 | Q26: On Completion | R26: Pending | U26: *** Billed under MD FINISHES (VAT MT25476001 / Mohammed Aldeeb), NOT MD Marble. Client VAT MT30717708. Confirm if it belongs in these books.
A27: MD-025 | B27: 45978 | C27: BURMARRAD GROUP PROPERTIES LIMITED | D27: Marsa | E27: Touch up & paint | F27: Paint (touch-up) | G27: Invoice | I27: 5000141 | J27: Service | K27: Yes | L27: 450 | M27: 81 | N27: 531 | O27: 0 | P27: =N27-O27 -> 531 | Q27: On Completion | R27: Pending | U27: *** Billed under MD FINISHES (Mohammed Aldeeb), NOT MD Marble. Same client as MD-024.
A28: MD-026 | B28: 45979 | C28: LAS VEGAS RESORT LTD | D28: Paceville (pool) | E28: Supply of 3cm Hammered Marble — extra pieces for the pool (ordered by Emmanuel) | F28: Hammered Marble 3cm | G28: Delivery-Invoice | I28: 1000259 | J28: Supply Only | K28: Yes | L28: 847.5 | M28: 152.55 | N28: 1000.05 | O28: 0 | P28: =N28-O28 -> 1000.05 | Q28: On Delivery | R28: Pending | U28: VAT MT28194902, Dragonara Rd, Paceville.
A29: MD-027 | B29: 45989 | C29: SUNSPOTS LTD | D29: Pieta | E29: Supply of Galala Marble for Lifts + Extras (ordered by Ezzideen) | F29: Galala | G29: Invoice | H29: 263 | I29: 400198 | J29: Supply Only | K29: Yes | L29: 2700 | M29: 486 | N29: 3186 | O29: 0 | P29: =N29-O29 -> 3186 | Q29: On Delivery | R29: Pending | U29: Same job across 3 docs (counted once): quoted as Q263 to contact "Albert" (Pieta) -> delivered via DN 1000260 -> fiscal Inv 400198. Gross 3,000 less 300 discount = 2,700 net.
A30: MD-028 | B30: 45992 | C30: ROGER SATARIANO & SON LTD | D30: Pool & BBQ area | E30: Supply & Install of Travertine for the pool & barbeque area | F30: Travertine | G30: Quotation | H30: 267 | J30: Supply & Install | K30: No | L30: 3780 | M30: 680.4 | N30: 4460.4 | O30: 0 | P30: =N30-O30 -> 4460.4 | Q30: Deposit on Confirmation | R30: Awaiting Confirmation | U30: VAT 1055-2337. New job, separate from the Mriehel Lava work (MD-010/MD-016).
A31: MD-029 | B31: 46007 | C31: JAA CO LTD | D31: Swieqi | E31: Supply of Crema Marfil — extra sills, 6 cut sizes (ordered by Ronaldo) | F31: Crema Marfil | G31: Invoice | H31: 268 | I31: 400205 | J31: Supply Only | K31: Yes | L31: 415 | M31: 74.7 | N31: 489.7 | O31: 0 | P31: =N31-O31 -> 489.7 | Q31: On Delivery | R31: Pending | U31: Quote 268 was confirmed & invoiced as Inv 400205 (16/12/2025). VAT MT2630-3713, Arzella, Swieqi.
A32: MD-030 | B32: 46067 | C32: WE MALTA LTD | D32: Attard | E32: Supply & Install of Biege Atone Marble — stairs (73.25 sqm) & skirting (64.40 lm), Ha Attard site | F32: Biege Atone | G32: Delivery-Invoice | H32: 272 | I32: 1000294 | J32: Supply & Install | K32: Yes | L32: 8030.55 | M32: 1445.5 | N32: 9476.05 | O32: 4245.17 | P32: =N32-O32 -> 5230.88 | Q32: On Completion | R32: Partial | U32: Quote 272 (orig €10,612.92) CONFIRMED & realised as Delivery-Invoice 1000294 (14/02/2026). Terms 40/30/30. 40% deposit €4,245.17 stated on doc (CONFIRM received); balance €5,230.88. VAT 26150532.
A33: MD-031 | B33: 45996 | C33: Purchase Order 1 (MARSA) | D33: Marsa (TBC) | E33: Supply & Install of Crema Galala — stairs, landing & entrance (65.6 sqm) + skirting | F33: Crema Galala | G33: Quotation | H33: 271 | J33: Supply & Install | K33: No | L33: 6935.8 | M33: 1248.44 | N33: 8184.24 | O33: 0 | P33: =N33-O33 -> 8184.24 | Q33: Deposit on Confirmation | R33: Awaiting Confirmation | U33: Doc customer literally "PURCHASE ORDER 1" (Marsa, no VAT) — identify the real client.
A34: MD-032 | B34: 46067 | C34: WE MALTA LTD | D34: Birkirkara | E34: Supply & Install of Biege Atone Marble — internal stairs (51.26 sqm) & internal skirting (62 lm), Birkirkara site | F34: Biege Atone | G34: Delivery-Invoice | H34: 273 | I34: 1000295 | J34: Supply & Install | K34: Yes | L34: 6231.5 | M34: 1121.67 | N34: 7353.17 | O34: 3364.7 | P34: =N34-O34 -> 3988.47 | Q34: On Completion | R34: Partial | U34: Quote 273 (orig €10,105.99) CONFIRMED & realised as Delivery-Invoice 1000295 (14/02/2026). 40% deposit €3,364.70 stated (CONFIRM received); doc states 60% balance €3,955.47 (deposit+balance = €7,320.17 vs total €7,353.17 — €33 rounding diff on doc). VAT 26150532.
A35: MD-033 | B35: 45999 | C35: Purchase Order 1 (MARSA) | D35: Penthouse (TBC) | E35: Supply & Install of Travertine Noce — penthouse (8.6 sqm) | F35: Travertine Noce | G35: Quotation | H35: 274 | J35: Supply & Install | K35: No | L35: 1088 | M35: 195.84 | N35: 1283.84 | O35: 0 | P35: =N35-O35 -> 1283.84 | Q35: Deposit on Confirmation | R35: Awaiting Confirmation | U35: Doc customer "PURCHASE ORDER 1" (Marsa, no VAT) — identify the real client.
A36: MD-034 | B36: 45999 | C36: UDRI INVESTMENTS LTD | D36: Attard | E36: Supply & Install of Bianco Marble — Attard site | F36: Bianco Marble | G36: Delivery-Invoice | I36: 1000265 | J36: Supply & Install | K36: Yes | L36: 1003.33 | M36: 180.6 | N36: 1183.93 | O36: 0 | P36: =N36-O36 -> 1183.93 | Q36: On Completion | R36: Pending | U36: VAT MT23109635, Msida Park, Msida.
A37: MD-035 | B37: 45999 | C37: UNITED INVESTMENT HOLDINGS LTD | D37: Attard | E37: Supply & Install of Bianco Marble — Attard site | F37: Bianco Marble | G37: Delivery-Invoice | I37: 1000266 | J37: Supply & Install | K37: Yes | L37: 2006.67 | M37: 361.2 | N37: 2367.87 | O37: 0 | P37: =N37-O37 -> 2367.87 | Q37: On Completion | R37: Pending | U37: VAT shows 00000 — confirm. 4 Timber Wharf, Marsa. Same Attard / Bianco job as UDRI (MD-034) — possibly linked.
A38: MD-036 | B38: 46000 | C38: ICI LIMITED | D38: Tal-Mandra (Villa 10) | E38: Supply & Install of Travertine & Bianco Marble — Villa 10 (internal entrance, sill, internal marble) | F38: Travertine & Bianco | G38: Invoice | I38: 400200 | J38: Supply & Install | K38: Yes | L38: 941 | M38: 169.38 | N38: 1110.38 | O38: 0 | P38: =N38-O38 -> 1110.38 | Q38: See Notes | R38: Pending | U38: VAT MT17813220. Payment split per doc: 80% cash €888.30 + 20% barter €222.08.
A39: MD-037 | B39: 46000 | C39: ICI LIMITED | D39: Tal-Mandra (Villa 11) | E39: Supply & Install of Travertine & Bianco Marble — Villa 11 (internal & external sills) | F39: Travertine & Bianco | G39: Invoice | I39: 400201 | J39: Supply & Install | K39: Yes | L39: 928 | M39: 167.04 | N39: 1095.04 | O39: 0 | P39: =N39-O39 -> 1095.04 | Q39: See Notes | R39: Pending | U39: VAT MT17813220. Payment split per doc: 80% cash €876.04 + 20% barter €219.
A40: MD-038 | B40: 45961 | C40: ICI LIMITED | D40: ICI site | E40: Supply of Travertine — material + cutting + round edges | F40: Travertine | G40: Invoice | I40: 400212 | J40: Supply Only | K40: Yes | L40: 845 | M40: 152.1 | N40: 997.1 | O40: 0 | P40: =N40-O40 -> 997.1 | Q40: On Delivery | R40: Pending | U40: VAT MT17813220. Older invoice (Oct-2025), added later.
A41: MD-039 | B41: 45995 | C41: ICI LIMITED | D41: Mosta | E41: Supply of Travertine crosscut sills — Mosta site (50 lm + 65 cm) | F41: Travertine crosscut | G41: Invoice | I41: 400210 | J41: Supply Only | K41: Yes | L41: 1162.35 | M41: 209.22 | N41: 1371.57 | O41: 0 | P41: =N41-O41 -> 1371.57 | Q41: See Notes | R41: Pending | U41: VAT MT17813220. Split: 80% cash €1,097.25 + 20% barter €274.30.
A42: MD-040 | B42: 45995 | C42: ICI LIMITED | D42: Pieta | E42: Supply of Travertine crosscut sills — Pieta site | F42: Travertine crosscut | G42: Invoice | I42: 400211 | J42: Supply Only | K42: Yes | L42: 1975 | M42: 355.5 | N42: 2330.5 | O42: 0 | P42: =N42-O42 -> 2330.5 | Q42: See Notes | R42: Pending | U42: VAT MT17813220. Split: 80% cash €1,864.40 + 20% barter €466.10.
A43: MD-041 | B43: 46000 | C43: ICI LIMITED | D43: Tal-Mandra (villas) | E43: Supply & Install of Travertine risers for entrances — Tal Mandra houses (villas V-3 to V-25) | F43: Travertine | G43: Invoice | I43: 400202 | J43: Supply & Install | K43: Yes | L43: 1510 | M43: 271.8 | N43: 1781.8 | O43: 0 | P43: =N43-O43 -> 1781.8 | Q43: See Notes | R43: Pending | U43: VAT MT17813220. Split: 80% cash €1,425.44 + 20% barter €356.36.
A44: MD-042 | B44: 46000 | C44: ICI LIMITED | D44: Tal-Mandra (Villa 25) | E44: Supply & Install of Bianco Marble — Villa 25 | F44: Bianco Marble | G44: Invoice | I44: 400203 | J44: Supply & Install | K44: Yes | L44: 1475 | M44: 265.5 | N44: 1740.5 | O44: 0 | P44: =N44-O44 -> 1740.5 | Q44: See Notes | R44: Pending | U44: VAT MT17813220. Split: 80% cash €1,392.40 + 20% barter €348.10.
A45: MD-043 | B45: 46000 | C45: ICI LIMITED | D45: Tal-Mandra (Villa 15) | E45: Supply & Install of Travertine & Bianco Marble — Villa 15 | F45: Travertine & Bianco | G45: Invoice | I45: 400204 | J45: Supply & Install | K45: Yes | L45: 962 | M45: 173.16 | N45: 1135.16 | O45: 0 | P45: =N45-O45 -> 1135.16 | Q45: See Notes | R45: Pending | U45: VAT MT17813220. Split: 80% cash €908.13 + 20% barter €227.03.
A46: MD-044 | B46: 46004 | C46: Purchase Order 1 (MARSA) | D46: Gharghur | E46: Supply & delivery of Travertine CrossCut — Gharghur | F46: Travertine crosscut | G46: Delivery-Invoice | I46: 1000268 | J46: Supply Only | K46: Yes | L46: 348.98 | M46: 62.82 | N46: 411.8 | O46: 0 | P46: =N46-O46 -> 411.8 | Q46: On Delivery | R46: Pending | U46: Gross 650 less 301.02 discount = 348.98 net. Client "PURCHASE ORDER 1" (Marsa, no VAT) — identify.
A47: MD-045 | B47: 46006 | C47: Robert (RMX Ltd) | D47: GF–Level 4 + Penthouse | E47: Supply of Biege stone marble for stairs (GF to Level 4) + Crema Galala for penthouse | F47: Biege stone / Crema Galala | G47: Delivery-Invoice | I47: 1000269 | J47: Supply Only | K47: Yes | L47: 5371 | M47: 966.78 | N47: 6337.78 | O47: 0 | P47: =N47-O47 -> 6337.78 | Q47: See Notes | R47: Pending | U47: Doc customer "RMX LTD" (Marsa, no VAT) = same as Robert/RMX (MD-015). Terms: 50% deposit / 50% on pickup.
A48: MD-046 | B48: 46006 | C48: Purchase Order 1 (MARSA) | D48: Marsa (TBC) | E48: Supply of Crema Galala & Tundra Marble — internal stairs/flooring, garden & façade walls, external stairs, sills, edges | F48: Crema Galala & Tundra | G48: Quotation | H48: 277 | J48: Supply Only | K48: No | L48: 11742.6 | M48: 2113.68 | N48: 13856.28 | O48: 0 | P48: =N48-O48 -> 13856.28 | Q48: Deposit on Confirmation | R48: Awaiting Confirmation | U48: Gross 12,032.60 less 290 discount = 11,742.60 net. Client "PURCHASE ORDER 1" — identify.
A49: MD-047 | B49: 46006 | C49: ROGER SATARIANO & SON LTD | D49: Ta Xbiex | E49: Supply of Biege stone marble for F0, F1, penthouse + roof — Ta Xbiex site | F49: Biege stone | G49: Delivery-Invoice | I49: 1000270 | J49: Supply Only | K49: Yes | L49: 812.5 | M49: 146.25 | N49: 958.75 | O49: 0 | P49: =N49-O49 -> 958.75 | Q49: On Delivery | R49: Pending | U49: VAT 1055-2337. New Ta Xbiex job.
A50: MD-048 | B50: 46011 | C50: ICI LIMITED | D50: Pembroke | E50: Supply of Travertine crosscut sills — Pembroke site | F50: Travertine crosscut | G50: Invoice | I50: 400208 | J50: Supply Only | K50: Yes | L50: 1874.69 | M50: 337.44 | N50: 2212.13 | O50: 0 | P50: =N50-O50 -> 2212.13 | Q50: See Notes | R50: Pending | U50: VAT MT17813220. Split: 80% cash €1,769.70 + 20% barter €442.43.
A51: MD-049 | B51: 46011 | C51: ICI LIMITED | D51: Pieta | E51: Supply of Travertine crosscut sills — Pieta site (ordered by Kevin) | F51: Travertine crosscut | G51: Invoice | I51: 400209 | J51: Supply Only | K51: Yes | L51: 644.46 | M51: 116 | N51: 760.46 | O51: 0 | P51: =N51-O51 -> 760.46 | Q51: See Notes | R51: Pending | U51: VAT MT17813220. Split: 80% cash €608.36 + 20% barter €152.10.
A52: MD-050 | B52: 46027 | C52: Purchase Order 1 (MARSA) | D52: Marsa (TBC) | E52: Supply of Bianco Carrera (5 pieces, 1.80×49 cm) | F52: Bianco Carrera | G52: Delivery-Invoice | I52: 1000273 | J52: Supply Only | K52: Yes | L52: 350 | M52: 63 | N52: 413 | O52: 0 | P52: =N52-O52 -> 413 | Q52: On Delivery | R52: Pending | U52: Client "PURCHASE ORDER 1" (Marsa, no VAT) — identify.
A53: MD-051 | B53: 46029 | C53: Purchase Order 1 (MARSA) | D53: Flat + Penthouse | E53: Supply of marble — flat, penthouse & stairs | F53: Marble | G53: Delivery-Invoice | I53: 1000274 | J53: Supply Only | K53: Yes | L53: 1855 | M53: 333.9 | N53: 2188.9 | O53: 0 | P53: =N53-O53 -> 2188.9 | Q53: On Delivery | R53: Pending | U53: Client "PURCHASE ORDER 1" (Marsa, no VAT) — identify.
A54: MD-052 | B54: 46031 | C54: CHARLES BORG | D54: Marsa | E54: Supply of marble | F54: Marble | G54: Invoice | I54: 400206 | J54: Supply Only | K54: Yes | L54: 1186.44 | M54: 213.56 | N54: 1400 | O54: 0 | P54: =N54-O54 -> 1400 | Q54: On Delivery | R54: Pending | U54: VAT 17757914, Marsa.
A55: MD-053 | B55: 46038 | C55: Purchase Order 1 (MARSA) | D55: 4 kitchens | E55: Supply & Install of Calacatta Vena Oro 12 mm — 4 kitchens | F55: Calacatta Vena Oro | G55: Delivery-Invoice | I55: 1000276 | J55: Supply & Install | K55: Yes | L55: 10600 | M55: 1908 | N55: 12508 | O55: 0 | P55: =N55-O55 -> 12508 | Q55: On Completion | R55: Pending | U55: Client "PURCHASE ORDER 1" (Marsa, no VAT) — identify. Large kitchen job (€12,508).
A56: MD-054 | B56: 46041 | C56: Purchase Order 1 (MARSA) | D56: Marsa (TBC) | E56: Supply & Install of Travertine + engraving (with material) | F56: Travertine | G56: Delivery-Invoice | I56: 1000279 | J56: Supply & Install | K56: Yes | L56: 701 | M56: 126.18 | N56: 827.18 | O56: 0 | P56: =N56-O56 -> 827.18 | Q56: On Completion | R56: Pending | U56: Client "PURCHASE ORDER 1" (Marsa, no VAT) — identify.
A57: MD-055 | B57: 46042 | C57: 1909 INVESTMENTS LTD | D57: Zebbug | E57: Supply & Install of Façade Travertine (40×60, 55 sqm) + Travertine stairs & entrance (198.6 sqm) | F57: Travertine | G57: Quotation | H57: 279 | J57: Supply & Install | K57: No | L57: 28277.6 | M57: 5089.97 | N57: 33367.57 | O57: 0 | P57: =N57-O57 -> 33367.57 | Q57: Deposit on Confirmation | R57: Awaiting Confirmation | U57: VAT 20541622. Large façade + stairs quote (€33,367.57). Existing client.
A58: MD-056 | B58: 46042 | C58: VGP PROPERTY INVESTMENT COMPANY LIMITED | D58: Xlendi, Gozo (Villas 1 & 2) | E58: Supply & Install of Alpha Biege thresholds & sills — Villas 1 & 2, Xlendi Gozo (incl. delivery to Gozo) | F58: Alpha Biege | G58: Delivery-Invoice | I58: 1000280 | J58: Supply & Install | K58: Yes | L58: 2458 | M58: 442.44 | N58: 2900.44 | O58: 0 | P58: =N58-O58 -> 2900.44 | Q58: On Completion | R58: Pending | U58: VAT 28035504, Naxxar. 50% deposit €1,450.22 noted on doc. Incl. €250 Gozo delivery.
A59: MD-057 | B59: 46044 | C59: Robert (RMX Ltd) | D59: Marsa | E59: Supply of Traonyx Marble (10.06 sqm) | F59: Traonyx | G59: Delivery-Invoice | I59: 1000282 | J59: Supply Only | K59: Yes | L59: 2515 | M59: 452.7 | N59: 2967.7 | O59: 0 | P59: =N59-O59 -> 2967.7 | Q59: On Delivery | R59: Pending | U59: Doc customer "Rober Rmx" = Robert (RMX Ltd).
A60: MD-058 | B60: 46045 | C60: ICI LIMITED | D60: Sliema Hotel | E60: Supply of Travertine — Sliema Hotel: Stairs+Landings 88.6 sqm @ €90, Skatlatora+Bastun 79 lm @ €20, Sills 8.2 sqm @ €90 | F60: Travertine | G60: Quotation | H60: 282 | J60: Supply Only | K60: No | L60: 10292 | M60: 1852.56 | N60: 12144.56 | O60: 0 | P60: =N60-O60 -> 12144.56 | Q60: Deposit on Confirmation | R60: Awaiting Confirmation | U60: Figures set to ISSUED Quote 282 PDF (23/01/2026) = €12,144.56 incl VAT. ⚠ Earlier workbook entry was €18,833.04 (larger scope incl walls/floors) — confirm if walls/floors are a separate quote. Pairs with installation Q285 (MD-060). VAT MT17813220.
A61: MD-059 | B61: 46049 | C61: ICI LIMITED | D61: Sliema Hotel | E61: Supply of Premium Travertine — Sliema Hotel @ €110/sqm | F61: Travertine (premium) | G61: Quotation | H61: 284 | J61: Supply Only | K61: No | L61: 19561 | M61: 3520.98 | N61: 23081.98 | O61: 0 | P61: =N61-O61 -> 23081.98 | Q61: Deposit on Confirmation | R61: Awaiting Confirmation | U61: SLIEMA HOTEL — SUPPLY OPTION B (premium @ €110/sqm). Alternative to Q282 (standard @ €90). Pairs with installation Q285.
A62: MD-060 | B62: 46049 | C62: ICI LIMITED | D62: Sliema Hotel | E62: Installation of Travertine — Sliema Hotel: Landings 48 sqm @ €36, Stairs+Skatlatora+Bastun 77 steps @ €38, Sills 8.2 sqm @ €38 | F62: Travertine | G62: Quotation | H62: 285 | J62: Service | K62: No | L62: 4965.6 | M62: 893.81 | N62: 5859.41 | O62: 0 | P62: =N62-O62 -> 5859.41 | Q62: Deposit on Confirmation | R62: Awaiting Confirmation | U62: Figures set to ISSUED Quote 285 PDF (27/01/2026) = €5,859.41 incl VAT. ⚠ Earlier workbook entry was €11,307.46 (larger scope) — confirm. Adds to supply Q282 (MD-058). VAT MT17813220.
A63: MD-061 | B63: 46053 | C63: Vince | D63: Fgura (block) | E63: Supply of Biege stone marble — stairs, risers, landings + Italian-style skirting | F63: Biege stone | G63: Quotation | H63: 286 | J63: Supply Only | K63: No | L63: 4284 | M63: 771.12 | N63: 5055.12 | O63: 0 | P63: =N63-O63 -> 5055.12 | Q63: Deposit on Confirmation | R63: Awaiting Confirmation | U63: VINCE FGURA BLOCK — SUPPLY OPTION A (Biege stone). Alternative to Q287 (Silvia). Pairs with installation Q288.
A64: MD-062 | B64: 46053 | C64: Vince | D64: Fgura (block) | E64: Supply of Silvia Marble — stairs, risers, landings + Italian-style skirting | F64: Silvia Marble | G64: Quotation | H64: 287 | J64: Supply Only | K64: No | L64: 4998 | M64: 899.64 | N64: 5897.64 | O64: 0 | P64: =N64-O64 -> 5897.64 | Q64: Deposit on Confirmation | R64: Awaiting Confirmation | U64: VINCE FGURA BLOCK — SUPPLY OPTION B (Silvia). Alternative to Q286 (Biege). Pairs with installation Q288.
A65: MD-063 | B65: 46053 | C65: Vince | D65: Fgura (block) | E65: Installation of stairs, landings & skirting — Fgura block | F65: Marble | G65: Quotation | H65: 288 | J65: Service | K65: No | L65: 3360 | M65: 604.8 | N65: 3964.8 | O65: 0 | P65: =N65-O65 -> 3964.8 | Q65: Deposit on Confirmation | R65: Awaiting Confirmation | U65: VINCE FGURA BLOCK — INSTALLATION quote (labour). Adds to whichever supply option (Q286 or Q287) is chosen.
A66: MD-064 | B66: 46055 | C66: Bahar ic-Caghaq (site) | D66: Bahar ic-Caghaq | E66: Supply of marble — Crema Marfil floors, brushed Crema Marfil bathrooms, travertine façade, Bianco Carrera sills | F66: Crema Marfil / Travertine / Bianco | G66: Quotation | H66: 290 | J66: Supply Only | K66: No | L66: 27012.75 | M66: 4862.3 | N66: 31875.05 | O66: 0 | P66: =N66-O66 -> 31875.05 | Q66: Deposit on Confirmation | R66: Awaiting Confirmation | U66: BAHAR IC-CAGHAQ JOB — SUPPLY. Pairs with installation Q291 (same areas). Large quote.
A67: MD-065 | B67: 46055 | C67: Bahar ic-Caghaq (site) | D67: Bahar ic-Caghaq | E67: Installation of marble floors, façade & sills | F67: Marble | G67: Quotation | H67: 291 | J67: Service | K67: No | L67: 9848.3 | M67: 1772.69 | N67: 11620.99 | O67: 0 | P67: =N67-O67 -> 11620.99 | Q67: Deposit on Confirmation | R67: Awaiting Confirmation | U67: BAHAR IC-CAGHAQ JOB — INSTALLATION (matches supply Q290 areas). Doc was labelled "PURCHASE ORDER 1" but it is the same job as Q290.
A68: MD-066 | B68: 46056 | C68: Rower Grech | D68: Marsa | E68: Supply of marble | F68: Marble | G68: Invoice | I68: 400213 | J68: Supply Only | K68: Yes | L68: 295 | M68: 53.1 | N68: 348.1 | O68: 0 | P68: =N68-O68 -> 348.1 | Q68: On Delivery | R68: Pending | U68: Doc customer "ROWER GRECH" (Marsa, no VAT) — confirm name/VAT.
A69: MD-067 | B69: 46056 | C69: Robert (RMX Ltd) | D69: San Gwann (penthouse) | E69: Supply of extra marble (ordered by Robert) — penthouse pieces | F69: Marble | G69: Delivery-Invoice | I69: 1000286 | J69: Supply Only | K69: Yes | L69: 270 | M69: 48.6 | N69: 318.6 | O69: 0 | P69: =N69-O69 -> 318.6 | Q69: On Delivery | R69: Pending | U69: Doc customer "Robert" (San Gwann); filename hint RMX = Robert (RMX Ltd). Extra pieces.
A70: MD-068 | B70: 46056 | C70: PROJECT TECHNIK LTD | D70: Qormi | E70: Supply & Install of Prestige Grey marble sills (70 lm) | F70: Prestige Grey | G70: Quotation | H70: 294 | J70: Supply & Install | K70: No | L70: 2310 | M70: 415.8 | N70: 2725.8 | O70: 0 | P70: =N70-O70 -> 2725.8 | Q70: Deposit on Confirmation | R70: Awaiting Confirmation | U70: PROJECT TECHNIK SILLS — material OPTION (Prestige Grey). Likely alternative to Grey Risen (Q295) & Travertine crosscut. NB: quote no. 294 was reused for two different quotes.
A71: MD-069 | B71: 46056 | C71: PROJECT TECHNIK LTD | D71: Qormi | E71: Supply & Install of Grey Risen marble sills (70 lm) | F71: Grey Risen | G71: Quotation | H71: 295 | J71: Supply & Install | K71: No | L71: 1960 | M71: 352.8 | N71: 2312.8 | O71: 0 | P71: =N71-O71 -> 2312.8 | Q71: Deposit on Confirmation | R71: Awaiting Confirmation | U71: PROJECT TECHNIK SILLS — material OPTION (Grey Risen). Alternative to Prestige Grey (Q294) & Travertine crosscut.
A72: MD-070 | B72: 46056 | C72: PROJECT TECHNIK LTD | D72: Qormi | E72: Supply & Install of Travertine crosscut sills (70 lm) | F72: Travertine crosscut | G72: Quotation | H72: 294 | J72: Supply & Install | K72: No | L72: 2170 | M72: 390.6 | N72: 2560.6 | O72: 0 | P72: =N72-O72 -> 2560.6 | Q72: Deposit on Confirmation | R72: Awaiting Confirmation | U72: PROJECT TECHNIK SILLS — material OPTION (Travertine crosscut). Shares quote no. 294 with the Prestige Grey quote (factory numbering error) — confirm.
A73: MD-071 | B73: 46056 | C73: Purchase Order 1 (MARSA) | D73: Marsa (TBC) | E73: Supply & Install of Lilac marble sink & backsplash | F73: Lilac Marble | G73: Quotation | H73: 296 | J73: Supply & Install | K73: No | L73: 1796 | M73: 323.28 | N73: 2119.28 | O73: 0 | P73: =N73-O73 -> 2119.28 | Q73: Deposit on Confirmation | R73: Awaiting Confirmation | U73: Client "PURCHASE ORDER 1" — identify. Install estimated €200–300.
A74: MD-072 | B74: 46057 | C74: Leon Debono | D74: Hal Ghaxaq | E74: Supply & Install of Creama Dino sills (incl. delivery) | F74: Creama Dino | G74: Quotation | H74: 297 | J74: Supply & Install | K74: No | L74: 615 | M74: 110.7 | N74: 725.7 | O74: 0 | P74: =N74-O74 -> 725.7 | Q74: Deposit on Confirmation | R74: Awaiting Confirmation | U74: VAT not on doc — confirm. Lifter & permits NOT included.
A75: MD-073 | B75: 46057 | C75: Mariestelle | D75: Zejtun | E75: Supply & Install of Prestige Grey stairs + skatlatora + bastun | F75: Prestige Grey | G75: Quotation | H75: 298 | J75: Supply & Install | K75: No | L75: 4277 | M75: 769.86 | N75: 5046.86 | O75: 0 | P75: =N75-O75 -> 5046.86 | Q75: Deposit on Confirmation | R75: Awaiting Confirmation | U75: Doc customer "Mariestelle" (Zejtun, no VAT) — confirm.
A76: MD-074 | B76: 46057 | C76: Purchase Order 1 (MARSA) | D76: Marsa (TBC) | E76: Supply & Install of Prestige Grey & Bianco Carrera — main + fire-exit staircases, roof/round/level sills | F76: Prestige Grey / Bianco Carrera | G76: Quotation | H76: 300 | J76: Supply & Install | K76: No | L76: 35967 | M76: 6474.06 | N76: 42441.06 | O76: 0 | P76: =N76-O76 -> 42441.06 | Q76: Deposit on Confirmation | R76: Awaiting Confirmation | U76: Client "PURCHASE ORDER 1" — identify. Largest open quote (€42,441.06).
A77: MD-075 | B77: 46059 | C77: GO PROPERTY LIMITED | D77: Pembroke (Triq il-Fortizza) | E77: Supply of Marble — Pembroke site | F77: Marble | G77: Invoice | I77: 400214 | J77: Supply Only | K77: Yes | L77: 8474.58 | M77: 1525.42 | N77: 10000 | O77: 0 | P77: =N77-O77 -> 10000 | Q77: On Delivery | R77: Pending | U77: VAT MT29919721, 148 Teal Court Flat 37, Triq Santa Venera, Msida. Fiscal invoice. Payable to Masoud Badr.
A78: MD-076 | B78: 46060 | C78: Purchase Order 1 (MARSA) | D78: Marsa (TBC) | E78: Supply & Install of Calacatta Viola Sink & Back Splash | F78: Calacatta Viola | G78: Quotation | H78: 301 | J78: Supply & Install | K78: No | L78: 3405 | M78: 612.9 | N78: 4017.9 | O78: 0 | P78: =N78-O78 -> 4017.9 | Q78: Deposit on Confirmation | R78: Awaiting Confirmation | U78: Doc customer "PURCHASE ORDER 1" (Marsa, no VAT) — identify client. Supply €3,205 + install €200 (install varies €200–300).
A79: MD-077 | B79: 46065 | C79: VGP PROPERTY INVESTMENT COMPANY LIMITED | D79: B1 The Windgates, Naxxar NXR2152 | E79: Supply of Bianco Carrera Sills, Triq Antonio Aguis Floriana | F79: Bianco Carrera | G79: Delivery-Invoice | H79: 303 | I79: 1000290 | J79: Supply & Install | K79: Yes | L79: 652.5 | M79: 117.45 | N79: 769.95 | O79: 0 | P79: =N79-O79 | Q79: On completion | R79: Invoiced | U79: Balance Due €769.95
A80: MD-078 | B80: 46060 | C80: ICI LIMITED | D80: Attard | E80: Supply of Travertine Crosscut Sills & Stairs | F80: Travertine Crosscut | G80: Delivery-Invoice | H80: 302 | I80: 1000307 | J80: Supply Only | K80: Yes | L80: 3631.66 | M80: 653.69 | N80: 4285.35 | O80: 0 | P80: =N80-O80 -> 4285.35 | Q80: On Delivery | R80: Invoiced | U80: VAT MT17813220. Sills 18–27cm 81.40lm@23; sills ≤17cm 7.20lm@19; sills >33cm 0.80sqm@90; install of sills €1,555. MEASURED — cut list in Measurement Pipeline (L-032). | Updated per Delivery-Invoice 1000307; old amounts flagged if different
A81: MD-079 | B81: 46060 | C81: VGP PROPERTY INVESTMENT COMPANY LIMITED | D81: Floriana | E81: Supply & Install of Marble — Sills & Stairs, F-1 to Roof Level | F81: Travertine / Marble | G81: Quotation | H81: 304 | J81: Supply & Install | K81: No | L81: 4595.55 | M81: 827.2 | N81: 5422.75 | O81: 0 | P81: =N81-O81 -> 5422.75 | Q81: Deposit on Confirmation | R81: Awaiting Confirmation | U81: VAT 28035504. Supply sills 22sqm@73 + stairs 12.2sqm@73; install sills €1,399.95 + stairs €549 + delivery €150. MEASURED — cut list in Measurement Pipeline (L-034).
A82: MD-080 | B82: 46055 | C82: Joesph Guzieppe Callus | D82: Mosta | E82: Supply & Install of Dino Brushed Stairs + Sills — Mosta site | F82: Dino Brushed / Beige Atone | G82: Quotation | H82: 292 | J82: Supply & Install | K82: No | L82: 6059 | M82: 1090.62 | N82: 7149.62 | O82: 0 | P82: =N82-O82 -> 7149.62 | Q82: Deposit on Confirmation | R82: Awaiting Confirmation | U82: Mosta (no VAT — confirm). Dino stairs+skirting 40sqm@90; install step+riser+skirting 45sqm@45; Dino/risen/beige-atone sills; install sills 12lm@17.
A83: MD-081 | B83: 46065 | C83: Maria | D83: Mosta (Il-Maxtura) | E83: Supply & Install of Taj Mahal Kitchen Top + Splash Back + Island (2cm) | F83: Taj Mahal | G83: Quotation | H83: 305 | J83: Supply & Install | K83: No | L83: 6270 | M83: 1128.6 | N83: 7398.6 | O83: 0 | P83: =N83-O83 -> 7398.6 | Q83: Deposit on Confirmation | R83: Awaiting Confirmation | U83: VAT 26849627, Il-Maxtura 1 Alley 2, Mosta. Kitchentop+splashback+island €5,630 + install €550 + delivery €50 + lifter €40.
A84: MD-082 | B84: 46067 | C84: Itiana | D84: Marsaskala | E84: Supply & Install of Travertine, Marsaskala (Multiple floors + Back Yard) | F84: Travertine | G84: Delivery-Invoice | H84: 306 | I84: 1000296 | J84: Supply & Install | K84: Yes | L84: 7794 | M84: 1402.92 | N84: 9196.92 | O84: 3678.76 | P84: =N84-O84 | Q84: On completion | R84: Partial | U84: 40% deposit €3,678.76 — confirm received
A85: MD-083 | B85: 46063 | C85: Naxxar (site) | D85: Naxxar | E85: Supply & Install of Marble Works | F85: Marble | G85: Delivery-Invoice | I85: 1000289 | J85: Supply & Install | K85: Yes | L85: 360 | M85: 64.8 | N85: 424.8 | O85: 0 | P85: =N85-O85 -> 424.8 | Q85: On Completion | R85: Pending | U85: Doc on "PURCHASE ORDER 1" template, customer "Naxxar" (no VAT) — identify. Delivery note (not fiscal). Payable to Masoud Badr.
A86: MD-084 | B86: 46060 | C86: May Grech | D86: Marsaxlokk (Triq il-Kuncizzjoni) | E86: Supply + Delivery of Marble — Marsaxlokk site (155 sqm) | F86: Marble | G86: Delivery-Invoice | H86: 289 | I86: 1000287 | J86: Supply Only | K86: Yes | L86: 10090.5 | M86: 1816.29 | N86: 11906.79 | O86: 4762.71 | P86: =N86-O86 -> 7144.08 | Q86: On Delivery | R86: Partial | U86: Marsaxlokk (no VAT — confirm). 155sqm @ €70 = €10,850 less €759.50 discount. 40% deposit €4,762.71 stated (CONFIRM received); balance €7,144.08 on delivery. Ref Quote 289. Payable to Masoud Badr.
A87: MD-085 | B87: 46066 | C87: ACTYF LTD | D87: Sliema (Tower Road) | E87: Supply & Install of Quarzite (behind reception) + Extra Travertine (near planter) | F87: Quarzite / Travertine | G87: Delivery-Invoice | I87: 1000293 | J87: Supply & Install | K87: Yes | L87: 2594 | M87: 466.92 | N87: 3060.92 | O87: 0 | P87: =N87-O87 -> 3060.92 | Q87: On Completion | R87: Pending | U87: VAT 21397311, 161D Tower Road, Sliema. Quarzite €765 + install €380 (light €180); extra travertine €1,017 + install €432. Delivery note. Payable to Masoud Badr.
A88: MD-086 | B88: 46066 | C88: WE MALTA LTD | D88: Birkirkara | E88: Supply & Install of Travertine for Entrances — Birkirkara | F88: Travertine | G88: Delivery-Invoice | I88: 1000291 | J88: Supply & Install | K88: Yes | L88: 1579.5 | M88: 284.31 | N88: 1863.81 | O88: 0 | P88: =N88-O88 -> 1863.81 | Q88: On Completion | R88: Pending | U88: VAT 26150532. Entrance 12.14sqm@85 + install 12.40sqm@34 + skirting 9lm + skirting install. Delivery note. Payable to Masoud Badr.
A89: MD-087 | B89: 46083 | C89: MSIDA | D89: Msida | E89: Supply & Install Bianco Carrara Sills (Roof Sills, Round Sills, Level 1+2+3+4, Install) | F89: Bianco Carrara | G89: Delivery-Invoice | H89: 309 | I89: 1000303 | J89: Supply & Install | K89: No | L89: 5452 | M89: 981.36 | N89: 6433.36 | O89: 2573.34 | P89: =N89-O89 | Q89: On confirmation | R89: Partial | U89: Q309 revised — original quote €17,941.43 (incl install + Round Sills). Invoice covers supply only, revised scope. Deposit €2,573.34 — confirm received.
A90: MD-088 | B90: 46067 | C90: GUDJA | D90: Gudja | E90: Supply & Install Staircase Beige (Stairs & Skirting) | F90: Beige Staircase | G90: Quotation | H90: 310 | J90: Supply & Install | K90: No | L90: 9336 | M90: 1680.48 | N90: 11016.48 | O90: 0 | P90: =N90-O90 | Q90: On confirmation | R90: Awaiting Confirmation | U90: Open quote — add to Measurement Pipeline
A91: MD-089 | B91: 46070 | C91: Cassar Ship Repair Ltd | D91: Slip No 6 Cross Road, Marsa | E91: Supply of Marble Sills | F91: Marble Sills | G91: Invoice | I91: 400215 | J91: Supply Only | K91: Yes | L91: 90 | M91: 16.2 | N91: 106.2 | O91: 0 | P91: =N91-O91 | Q91: On Delivery | R91: Invoiced | U91: VAT MT11461431 — Supply only — paid on delivery
A92: MD-090 | B92: 46070 | C92: May Grech | D92: Marsaxlokk | E92: Supply of Marble for Penthouse | F92: Marble | G92: Delivery-Invoice | I92: 1000298 | J92: Supply Only | K92: Yes | L92: 370 | M92: 66.6 | N92: 436.6 | O92: 0 | P92: =N92-O92 | Q92: On Delivery | R92: Invoiced | U92: Supply only — paid on delivery
A93: MD-091 | B93: 46071 | C93: Malta International Airport PLC | D93: Luqa LQA 4000 | E93: Supply & Delivery of Lime Stone Sills (10m x 14cm + Delivery) | F93: Lime Stone | G93: Delivery-Invoice | H93: 299 | I93: 1000299 | J93: Supply Only | K93: Yes | L93: 285 | M93: 51.3 | N93: 336.3 | O93: 0 | P93: =N93-O93 | Q93: On Delivery | R93: Invoiced | U93: Supply only — paid on delivery
A94: MD-092 | B94: 46074 | C94: Stalagmite Connections | D94: Mqabba | E94: Supply of Marble Stair Fgura Etienne — Deposit | F94: Marble Stair | G94: Invoice | I94: 400217 | J94: Supply & Install | K94: Yes | L94: 423.73 | M94: 76.27 | N94: 500 | O94: 500 | P94: =N94-O94 | Q94: Deposit on Confirmation | R94: Partial | U94: VAT 18130814 — Deposit invoice — confirm received; full balance due on completion
A95: MD-093 | B95: 46074 | C95: Blane | D95: Santa Lucia | E95: Supply of Crema Marfil Sills + Delivery, Santa Lucia | F95: Crema Marfil | G95: Quotation | H95: 317 | J95: Supply Only | K95: No | L95: 467.5 | M95: 84.15 | N95: 551.65 | O95: 0 | P95: =N95-O95 | Q95: Deposit on Confirmation | R95: Awaiting Confirmation | U95: Open quote — add to Measurement Pipeline
A96: MD-094 | B96: 46074 | C96: MARSA | D96: Marsa | E96: Supply of Crema Galala Sills + Delivery | F96: Crema Galala | G96: Quotation | H96: 318 | J96: Supply Only | K96: No | L96: 387.5 | M96: 69.75 | N96: 457.25 | O96: 0 | P96: =N96-O96 | Q96: Deposit on Confirmation | R96: Awaiting Confirmation | U96: Client name not on document — confirm client name
A97: MD-095 | B97: 46078 | C97: JAA CO LTD | D97: Arzella Xitwija, Triq Gizi, Swieqi | E97: Supply of Marble Marsaskala | F97: Marble | G97: Delivery-Invoice | I97: 1000302 | J97: Supply Only | K97: Yes | L97: 11533.18 | M97: 2075.97 | N97: 13609.15 | O97: 13609.15 | P97: =N97-O97 | Q97: On Delivery | R97: Invoiced | U97: Amounts corrected per revised PDF. Old entry: €13,609.16 excl / €16,058.81 incl.
A98: MD-096 | B98: 46076 | C98: Gordon Vella | D98: Msida | E98: Supply of Light Travertine Sills (Sills, Stairs, Entrance) | F98: Light Travertine | G98: Quotation | H98: 323 | J98: Supply Only | K98: No | L98: 20986.2 | M98: 3777.52 | N98: 24763.72 | O98: 0 | P98: =N98-O98 | Q98: Deposit on Confirmation | R98: Awaiting Confirmation | U98: Open quote — add to Measurement Pipeline
A99: MD-097 | B99: 46079 | C99: BJORN | D99: Zabbar | E99: Supply & Install Bianco Marble & Nero Assaluto | F99: Bianco Marble / Nero Assaluto | G99: Quotation | H99: 324 | J99: Supply & Install | K99: No | L99: 4300 | M99: 774 | N99: 5074 | O99: 0 | P99: =N99-O99 | Q99: Deposit on Confirmation | R99: Awaiting Confirmation | U99: Open quote — add to Measurement Pipeline
A100: MD-098 | B100: 46079 | C100: BJORN | D100: Zabbar | E100: Supply & Install Quarzite & Crema Marfil Marble (back light included with installation) | F100: Quarzite / Crema Marfil | G100: Quotation | H100: 325 | J100: Supply & Install | K100: No | L100: 6680 | M100: 1202.4 | N100: 7882.4 | O100: 0 | P100: =N100-O100 | Q100: Deposit on Confirmation | R100: Awaiting Confirmation | U100: Open quote — back light included with installation; add to Measurement Pipeline
...

Sheet Client Directory
A1: CLIENT DIRECTORY
A2: Client ID | B2: Client Name | C2: VAT No. | D2: Location / Address | E2: Contact (phone / email) | F2: Client Type | G2: First Job | H2: # Docs | I2: Total Quoted | J2: Total Invoiced | K2: Received | L2: Outstanding | M2: Materials / Notes
A3: C-001 | B3: WE MALTA LTD | C3: 26150532 | D3: Isabella Court Flt, Triq il-Mejjiesa, Birkirkara | F3: Developer / Contractor | G3: 45905 | H3: =COUNTIF('Orders & Payments'!$C$3:$C$200,$B3) -> 4 | I3: =SUMIFS('Orders & Payments'!$N$3:$N$200,'Orders & Payments'!$C$3:$C$200,$B3,'Orders & Payments'!$G$3:$G$200,"Quotation") -> 0 | J3: =SUMIFS('Orders & Payments'!$N$3:$N$200,'Orders & Payments'!$C$3:$C$200,$B3,'Orders & Payments'!$G$3:$G$200,"Invoice")+SUMIFS('Orders & Payments'!$N$3:$N$200,'Orders & Payments'!$C$3:$C$200,$B3,'Orders & Payments'!$G$3:$G$200,"Delivery-Invoice") -> 20321.43 | K3: =SUMIFS('Orders & Payments'!$O$3:$O$200,'Orders & Payments'!$C$3:$C$200,$B3) -> 7609.87 | L3: =SUMIFS('Orders & Payments'!$P$3:$P$200,'Orders & Payments'!$C$3:$C$200,$B3,'Orders & Payments'!$G$3:$G$200,"Invoice")+SUMIFS('Orders & Payments'!$P$3:$P$200,'Orders & Payments'!$C$3:$C$200,$B3,'Orders & Payments'!$G$3:$G$200,"Delivery-Invoice") -> 12711.56 | M3: Biege stone lift cladding (Pieta).
A4: C-002 | B4: AX CONSTRUCTION LIMITED | C4: 12949330 | D4: Triq id-Difiza Civili, Mosta MST1741 | F4: Construction Co. | G4: 45918 | H4: =COUNTIF('Orders & Payments'!$C$3:$C$200,$B4) -> 1 | I4: =SUMIFS('Orders & Payments'!$N$3:$N$200,'Orders & Payments'!$C$3:$C$200,$B4,'Orders & Payments'!$G$3:$G$200,"Quotation") -> 0 | J4: =SUMIFS('Orders & Payments'!$N$3:$N$200,'Orders & Payments'!$C$3:$C$200,$B4,'Orders & Payments'!$G$3:$G$200,"Invoice")+SUMIFS('Orders & Payments'!$N$3:$N$200,'Orders & Payments'!$C$3:$C$200,$B4,'Orders & Payments'!$G$3:$G$200,"Delivery-Invoice") -> 265.5 | K4: =SUMIFS('Orders & Payments'!$O$3:$O$200,'Orders & Payments'!$C$3:$C$200,$B4) -> 0 | L4: =SUMIFS('Orders & Payments'!$P$3:$P$200,'Orders & Payments'!$C$3:$C$200,$B4,'Orders & Payments'!$G$3:$G$200,"Invoice")+SUMIFS('Orders & Payments'!$P$3:$P$200,'Orders & Payments'!$C$3:$C$200,$B4,'Orders & Payments'!$G$3:$G$200,"Delivery-Invoice") -> 265.5 | M4: Biege limestone (Airport).
A5: C-003 | B5: 1909 INVESTMENTS LTD | C5: 20541622 | D5: BG House No.3, Triq Guliernu Lorenzi, Zebbug | F5: Developer | G5: 45926 | H5: =COUNTIF('Orders & Payments'!$C$3:$C$200,$B5) -> 4 | I5: =SUMIFS('Orders & Payments'!$N$3:$N$200,'Orders & Payments'!$C$3:$C$200,$B5,'Orders & Payments'!$G$3:$G$200,"Quotation") -> 33367.57 | J5: =SUMIFS('Orders & Payments'!$N$3:$N$200,'Orders & Payments'!$C$3:$C$200,$B5,'Orders & Payments'!$G$3:$G$200,"Invoice")+SUMIFS('Orders & Payments'!$N$3:$N$200,'Orders & Payments'!$C$3:$C$200,$B5,'Orders & Payments'!$G$3:$G$200,"Delivery-Invoice") -> 17053.73 | K5: =SUMIFS('Orders & Payments'!$O$3:$O$200,'Orders & Payments'!$C$3:$C$200,$B5) -> 0 | L5: =SUMIFS('Orders & Payments'!$P$3:$P$200,'Orders & Payments'!$C$3:$C$200,$B5,'Orders & Payments'!$G$3:$G$200,"Invoice")+SUMIFS('Orders & Payments'!$P$3:$P$200,'Orders & Payments'!$C$3:$C$200,$B5,'Orders & Payments'!$G$3:$G$200,"Delivery-Invoice") -> 17053.73 | M5: Travertine sills & stairs across 12 flats. Incl. 1 credit note (vs Inv 400190).
A6: C-004 | B6: SUNSPOTS LTD | C6: 12527802 | D6: St Julians | F6: Developer / Contractor | G6: 45929 | H6: =COUNTIF('Orders & Payments'!$C$3:$C$200,$B6) -> 2 | I6: =SUMIFS('Orders & Payments'!$N$3:$N$200,'Orders & Payments'!$C$3:$C$200,$B6,'Orders & Payments'!$G$3:$G$200,"Quotation") -> 0 | J6: =SUMIFS('Orders & Payments'!$N$3:$N$200,'Orders & Payments'!$C$3:$C$200,$B6,'Orders & Payments'!$G$3:$G$200,"Invoice")+SUMIFS('Orders & Payments'!$N$3:$N$200,'Orders & Payments'!$C$3:$C$200,$B6,'Orders & Payments'!$G$3:$G$200,"Delivery-Invoice") -> 6726 | K6: =SUMIFS('Orders & Payments'!$O$3:$O$200,'Orders & Payments'!$C$3:$C$200,$B6) -> 0 | L6: =SUMIFS('Orders & Payments'!$P$3:$P$200,'Orders & Payments'!$C$3:$C$200,$B6,'Orders & Payments'!$G$3:$G$200,"Invoice")+SUMIFS('Orders & Payments'!$P$3:$P$200,'Orders & Payments'!$C$3:$C$200,$B6,'Orders & Payments'!$G$3:$G$200,"Delivery-Invoice") -> 6726 | M6: Travertine + Galala sills & stairs (Pieta).
A7: C-005 | B7: ROGER SATARIANO & SON LTD | C7: 1055-2337 | D7: 122 Msida Valley Road, Birkirkara | F7: Contractor | G7: 45931 | H7: =COUNTIF('Orders & Payments'!$C$3:$C$200,$B7) -> 4 | I7: =SUMIFS('Orders & Payments'!$N$3:$N$200,'Orders & Payments'!$C$3:$C$200,$B7,'Orders & Payments'!$G$3:$G$200,"Quotation") -> 9569.8 | J7: =SUMIFS('Orders & Payments'!$N$3:$N$200,'Orders & Payments'!$C$3:$C$200,$B7,'Orders & Payments'!$G$3:$G$200,"Invoice")+SUMIFS('Orders & Payments'!$N$3:$N$200,'Orders & Payments'!$C$3:$C$200,$B7,'Orders & Payments'!$G$3:$G$200,"Delivery-Invoice") -> 1271.45 | K7: =SUMIFS('Orders & Payments'!$O$3:$O$200,'Orders & Payments'!$C$3:$C$200,$B7) -> 0 | L7: =SUMIFS('Orders & Payments'!$P$3:$P$200,'Orders & Payments'!$C$3:$C$200,$B7,'Orders & Payments'!$G$3:$G$200,"Invoice")+SUMIFS('Orders & Payments'!$P$3:$P$200,'Orders & Payments'!$C$3:$C$200,$B7,'Orders & Payments'!$G$3:$G$200,"Delivery-Invoice") -> 1271.45 | M7: Lava Black stairs & façade + extra Lava door sills (Mriehel).
A8: C-006 | B8: ICI LIMITED | C8: MT17813220 | D8: Triq l-Artigjanat Zone 4, Birkirkara Centre | F8: Contractor | G8: 45936 | H8: =COUNTIF('Orders & Payments'!$C$3:$C$200,$B8) -> 17 | I8: =SUMIFS('Orders & Payments'!$N$3:$N$200,'Orders & Payments'!$C$3:$C$200,$B8,'Orders & Payments'!$G$3:$G$200,"Quotation") -> 45937.7 | J8: =SUMIFS('Orders & Payments'!$N$3:$N$200,'Orders & Payments'!$C$3:$C$200,$B8,'Orders & Payments'!$G$3:$G$200,"Invoice")+SUMIFS('Orders & Payments'!$N$3:$N$200,'Orders & Payments'!$C$3:$C$200,$B8,'Orders & Payments'!$G$3:$G$200,"Delivery-Invoice") -> 16292.84 | K8: =SUMIFS('Orders & Payments'!$O$3:$O$200,'Orders & Payments'!$C$3:$C$200,$B8) -> 0 | L8: =SUMIFS('Orders & Payments'!$P$3:$P$200,'Orders & Payments'!$C$3:$C$200,$B8,'Orders & Payments'!$G$3:$G$200,"Invoice")+SUMIFS('Orders & Payments'!$P$3:$P$200,'Orders & Payments'!$C$3:$C$200,$B8,'Orders & Payments'!$G$3:$G$200,"Delivery-Invoice") -> 16292.84 | M8: Travertine supply; Villa Fiorini sill replacement; touch-up & paint (Sliema).
A9: C-007 | B9: PROJECT TECHNIK LTD | C9: MT19667814 | D9: Cannon Road, Qormi QRM9032 | F9: Contractor | G9: 45966 | H9: =COUNTIF('Orders & Payments'!$C$3:$C$200,$B9) -> 4 | I9: =SUMIFS('Orders & Payments'!$N$3:$N$200,'Orders & Payments'!$C$3:$C$200,$B9,'Orders & Payments'!$G$3:$G$200,"Quotation") -> 7599.2 | J9: =SUMIFS('Orders & Payments'!$N$3:$N$200,'Orders & Payments'!$C$3:$C$200,$B9,'Orders & Payments'!$G$3:$G$200,"Invoice")+SUMIFS('Orders & Payments'!$N$3:$N$200,'Orders & Payments'!$C$3:$C$200,$B9,'Orders & Payments'!$G$3:$G$200,"Delivery-Invoice") -> 1752.3 | K9: =SUMIFS('Orders & Payments'!$O$3:$O$200,'Orders & Payments'!$C$3:$C$200,$B9) -> 0 | L9: =SUMIFS('Orders & Payments'!$P$3:$P$200,'Orders & Payments'!$C$3:$C$200,$B9,'Orders & Payments'!$G$3:$G$200,"Invoice")+SUMIFS('Orders & Payments'!$P$3:$P$200,'Orders & Payments'!$C$3:$C$200,$B9,'Orders & Payments'!$G$3:$G$200,"Delivery-Invoice") -> 1752.3 | M9: Trista Grey supply.
A10: C-008 | B10: STEPHEN FARRUGIA | C10: mt13709420 | D10: 59 The Orchids, Triq is-Soll, Santa Venera | F10: Private | G10: 45975 | H10: =COUNTIF('Orders & Payments'!$C$3:$C$200,$B10) -> 1 | I10: =SUMIFS('Orders & Payments'!$N$3:$N$200,'Orders & Payments'!$C$3:$C$200,$B10,'Orders & Payments'!$G$3:$G$200,"Quotation") -> 0 | J10: =SUMIFS('Orders & Payments'!$N$3:$N$200,'Orders & Payments'!$C$3:$C$200,$B10,'Orders & Payments'!$G$3:$G$200,"Invoice")+SUMIFS('Orders & Payments'!$N$3:$N$200,'Orders & Payments'!$C$3:$C$200,$B10,'Orders & Payments'!$G$3:$G$200,"Delivery-Invoice") -> 8283.6 | K10: =SUMIFS('Orders & Payments'!$O$3:$O$200,'Orders & Payments'!$C$3:$C$200,$B10) -> 0 | L10: =SUMIFS('Orders & Payments'!$P$3:$P$200,'Orders & Payments'!$C$3:$C$200,$B10,'Orders & Payments'!$G$3:$G$200,"Invoice")+SUMIFS('Orders & Payments'!$P$3:$P$200,'Orders & Payments'!$C$3:$C$200,$B10,'Orders & Payments'!$G$3:$G$200,"Delivery-Invoice") -> 8283.6 | M10: Marble supply & install. Project €13,806; balance €8,283.60 outstanding (deposit paid).
A11: C-009 | B11: Luqa New Airport | C11: — (confirm) | D11: Luqa Airport project | F11: Project / Site | G11: 45625 | H11: =COUNTIF('Orders & Payments'!$C$3:$C$200,$B11) -> 1 | I11: =SUMIFS('Orders & Payments'!$N$3:$N$200,'Orders & Payments'!$C$3:$C$200,$B11,'Orders & Payments'!$G$3:$G$200,"Quotation") -> 7791.92 | J11: =SUMIFS('Orders & Payments'!$N$3:$N$200,'Orders & Payments'!$C$3:$C$200,$B11,'Orders & Payments'!$G$3:$G$200,"Invoice")+SUMIFS('Orders & Payments'!$N$3:$N$200,'Orders & Payments'!$C$3:$C$200,$B11,'Orders & Payments'!$G$3:$G$200,"Delivery-Invoice") -> 0 | K11: =SUMIFS('Orders & Payments'!$O$3:$O$200,'Orders & Payments'!$C$3:$C$200,$B11) -> 0 | L11: =SUMIFS('Orders & Payments'!$P$3:$P$200,'Orders & Payments'!$C$3:$C$200,$B11,'Orders & Payments'!$G$3:$G$200,"Invoice")+SUMIFS('Orders & Payments'!$P$3:$P$200,'Orders & Payments'!$C$3:$C$200,$B11,'Orders & Payments'!$G$3:$G$200,"Delivery-Invoice") -> 0 | M11: Biege lime stone supply & install — old quote, confirm status.
A12: C-010 | B12: Qrendi (site) | C12: — (confirm) | D12: Qrendi | F12: Project / Site | G12: 45868 | H12: =COUNTIF('Orders & Payments'!$C$3:$C$200,$B12) -> 1 | I12: =SUMIFS('Orders & Payments'!$N$3:$N$200,'Orders & Payments'!$C$3:$C$200,$B12,'Orders & Payments'!$G$3:$G$200,"Quotation") -> 1910.42 | J12: =SUMIFS('Orders & Payments'!$N$3:$N$200,'Orders & Payments'!$C$3:$C$200,$B12,'Orders & Payments'!$G$3:$G$200,"Invoice")+SUMIFS('Orders & Payments'!$N$3:$N$200,'Orders & Payments'!$C$3:$C$200,$B12,'Orders & Payments'!$G$3:$G$200,"Delivery-Invoice") -> 0 | K12: =SUMIFS('Orders & Payments'!$O$3:$O$200,'Orders & Payments'!$C$3:$C$200,$B12) -> 0 | L12: =SUMIFS('Orders & Payments'!$P$3:$P$200,'Orders & Payments'!$C$3:$C$200,$B12,'Orders & Payments'!$G$3:$G$200,"Invoice")+SUMIFS('Orders & Payments'!$P$3:$P$200,'Orders & Payments'!$C$3:$C$200,$B12,'Orders & Payments'!$G$3:$G$200,"Delivery-Invoice") -> 0 | M12: Marble slab supply quote — confirm client name & VAT.
A13: C-011 | B13: Marsa – Hand-Crafted Job | C13: — (confirm) | D13: Marsa | F13: Private / TBC | G13: 45917 | H13: =COUNTIF('Orders & Payments'!$C$3:$C$200,$B13) -> 1 | I13: =SUMIFS('Orders & Payments'!$N$3:$N$200,'Orders & Payments'!$C$3:$C$200,$B13,'Orders & Payments'!$G$3:$G$200,"Quotation") -> 4448.6 | J13: =SUMIFS('Orders & Payments'!$N$3:$N$200,'Orders & Payments'!$C$3:$C$200,$B13,'Orders & Payments'!$G$3:$G$200,"Invoice")+SUMIFS('Orders & Payments'!$N$3:$N$200,'Orders & Payments'!$C$3:$C$200,$B13,'Orders & Payments'!$G$3:$G$200,"Delivery-Invoice") -> 0 | K13: =SUMIFS('Orders & Payments'!$O$3:$O$200,'Orders & Payments'!$C$3:$C$200,$B13) -> 0 | L13: =SUMIFS('Orders & Payments'!$P$3:$P$200,'Orders & Payments'!$C$3:$C$200,$B13,'Orders & Payments'!$G$3:$G$200,"Invoice")+SUMIFS('Orders & Payments'!$P$3:$P$200,'Orders & Payments'!$C$3:$C$200,$B13,'Orders & Payments'!$G$3:$G$200,"Delivery-Invoice") -> 0 | M13: Hand-crafted marble designs quote (doc labelled "MARSA").
A14: C-012 | B14: Robert (RMX Ltd) | C14: — (confirm) | D14: Marsa | F14: TBC | G14: 45965 | H14: =COUNTIF('Orders & Payments'!$C$3:$C$200,$B14) -> 4 | I14: =SUMIFS('Orders & Payments'!$N$3:$N$200,'Orders & Payments'!$C$3:$C$200,$B14,'Orders & Payments'!$G$3:$G$200,"Quotation") -> 0 | J14: =SUMIFS('Orders & Payments'!$N$3:$N$200,'Orders & Payments'!$C$3:$C$200,$B14,'Orders & Payments'!$G$3:$G$200,"Invoice")+SUMIFS('Orders & Payments'!$N$3:$N$200,'Orders & Payments'!$C$3:$C$200,$B14,'Orders & Payments'!$G$3:$G$200,"Delivery-Invoice") -> 12338.08 | K14: =SUMIFS('Orders & Payments'!$O$3:$O$200,'Orders & Payments'!$C$3:$C$200,$B14) -> 0 | L14: =SUMIFS('Orders & Payments'!$P$3:$P$200,'Orders & Payments'!$C$3:$C$200,$B14,'Orders & Payments'!$G$3:$G$200,"Invoice")+SUMIFS('Orders & Payments'!$P$3:$P$200,'Orders & Payments'!$C$3:$C$200,$B14,'Orders & Payments'!$G$3:$G$200,"Delivery-Invoice") -> 12338.08 | M14: Silvia marble supply (doc labelled "MARSA"; filename: Robert/RMX).
... A39: C-037 | B39: Naxxar (site) | C39: — (confirm) | D39: Naxxar | F39: Project / Site (TBC) | G39: 46063 | H39: =COUNTIF('Orders & Payments'!$C$3:$C$200,$B39) -> 1 | I39: =SUMIFS('Orders & Payments'!$N$3:$N$200,'Orders & Payments'!$C$3:$C$200,$B39,'Orders & Payments'!$G$3:$G$200,"Quotation") -> 0 | J39: =SUMIFS('Orders & Payments'!$N$3:$N$200,'Orders & Payments'!$C$3:$C$200,$B39,'Orders & Payments'!$G$3:$G$200,"Invoice")+SUMIFS('Orders & Payments'!$N$3:$N$200,'Orders & Payments'!$C$3:$C$200,$B39,'Orders & Payments'!$G$3:$G$200,"Delivery-Invoice") -> 424.8 | K39: =SUMIFS('Orders & Payments'!$O$3:$O$200,'Orders & Payments'!$C$3:$C$200,$B39) -> 0 | L39: =SUMIFS('Orders & Payments'!$P$3:$P$200,'Orders & Payments'!$C$3:$C$200,$B39,'Orders & Payments'!$G$3:$G$200,"Invoice")+SUMIFS('Orders & Payments'!$P$3:$P$200,'Orders & Payments'!$C$3:$C$200,$B39,'Orders & Payments'!$G$3:$G$200,"Delivery-Invoice") -> 424.8 | M39: Small supply & install (Inv 1000289). Doc on "Purchase Order 1" template — identify client.
A40: C-038 | B40: MSIDA | C40: — (confirm) | D40: Msida | F40: Private / TBC | G40: 46067 | H40: =COUNTIF('Orders & Payments'!$C$3:$C$200,$B40) | I40: =SUMIFS('Orders & Payments'!$N$3:$N$200,'Orders & Payments'!$C$3:$C$200,$B40,'Orders & Payments'!$G$3:$G$200,"Quotation") | J40: =SUMIFS('Orders & Payments'!$N$3:$N$200,'Orders & Payments'!$C$3:$C$200,$B40,'Orders & Payments'!$G$3:$G$200,"Invoice")+SUMIFS('Orders & Payments'!$N$3:$N$200,'Orders & Payments'!$C$3:$C$200,$B40,'Orders & Payments'!$G$3:$G$200,"Delivery-Invoice") | K40: =SUMIFS('Orders & Payments'!$O$3:$O$200,'Orders & Payments'!$C$3:$C$200,$B40) | L40: =SUMIFS('Orders & Payments'!$P$3:$P$200,'Orders & Payments'!$C$3:$C$200,$B40,'Orders & Payments'!$G$3:$G$200,"Invoice")+SUMIFS('Orders & Payments'!$P$3:$P$200,'Orders & Payments'!$C$3:$C$200,$B40,'Orders & Payments'!$G$3:$G$200,"Delivery-Invoice")
A41: C-039 | B41: GUDJA | C41: — (confirm) | D41: Gudja | F41: Private / TBC | G41: 46067 | H41: =COUNTIF('Orders & Payments'!$C$3:$C$200,$B41) | I41: =SUMIFS('Orders & Payments'!$N$3:$N$200,'Orders & Payments'!$C$3:$C$200,$B41,'Orders & Payments'!$G$3:$G$200,"Quotation") | J41: =SUMIFS('Orders & Payments'!$N$3:$N$200,'Orders & Payments'!$C$3:$C$200,$B41,'Orders & Payments'!$G$3:$G$200,"Invoice")+SUMIFS('Orders & Payments'!$N$3:$N$200,'Orders & Payments'!$C$3:$C$200,$B41,'Orders & Payments'!$G$3:$G$200,"Delivery-Invoice") | K41: =SUMIFS('Orders & Payments'!$O$3:$O$200,'Orders & Payments'!$C$3:$C$200,$B41) | L41: =SUMIFS('Orders & Payments'!$P$3:$P$200,'Orders & Payments'!$C$3:$C$200,$B41,'Orders & Payments'!$G$3:$G$200,"Invoice")+SUMIFS('Orders & Payments'!$P$3:$P$200,'Orders & Payments'!$C$3:$C$200,$B41,'Orders & Payments'!$G$3:$G$200,"Delivery-Invoice")
A42: C-040 | B42: Cassar Ship Repair Ltd | C42: MT11461431 | D42: Slip No 6 Cross Road, Marsa | F42: Contractor | G42: 46070 | H42: =COUNTIF('Orders & Payments'!$C$3:$C$200,$B42) | I42: =SUMIFS('Orders & Payments'!$N$3:$N$200,'Orders & Payments'!$C$3:$C$200,$B42,'Orders & Payments'!$G$3:$G$200,"Quotation") | J42: =SUMIFS('Orders & Payments'!$N$3:$N$200,'Orders & Payments'!$C$3:$C$200,$B42,'Orders & Payments'!$G$3:$G$200,"Invoice")+SUMIFS('Orders & Payments'!$N$3:$N$200,'Orders & Payments'!$C$3:$C$200,$B42,'Orders & Payments'!$G$3:$G$200,"Delivery-Invoice") | K42: =SUMIFS('Orders & Payments'!$O$3:$O$200,'Orders & Payments'!$C$3:$C$200,$B42) | L42: =SUMIFS('Orders & Payments'!$P$3:$P$200,'Orders & Payments'!$C$3:$C$200,$B42,'Orders & Payments'!$G$3:$G$200,"Invoice")+SUMIFS('Orders & Payments'!$P$3:$P$200,'Orders & Payments'!$C$3:$C$200,$B42,'Orders & Payments'!$G$3:$G$200,"Delivery-Invoice")
A43: C-041 | B43: Malta International Airport PLC | C43: — (confirm) | D43: Luqa LQA 4000 | F43: Corporate / Airport | G43: 46071 | H43: =COUNTIF('Orders & Payments'!$C$3:$C$200,$B43) | I43: =SUMIFS('Orders & Payments'!$N$3:$N$200,'Orders & Payments'!$C$3:$C$200,$B43,'Orders & Payments'!$G$3:$G$200,"Quotation") | J43: =SUMIFS('Orders & Payments'!$N$3:$N$200,'Orders & Payments'!$C$3:$C$200,$B43,'Orders & Payments'!$G$3:$G$200,"Invoice")+SUMIFS('Orders & Payments'!$N$3:$N$200,'Orders & Payments'!$C$3:$C$200,$B43,'Orders & Payments'!$G$3:$G$200,"Delivery-Invoice") | K43: =SUMIFS('Orders & Payments'!$O$3:$O$200,'Orders & Payments'!$C$3:$C$200,$B43) | L43: =SUMIFS('Orders & Payments'!$P$3:$P$200,'Orders & Payments'!$C$3:$C$200,$B43,'Orders & Payments'!$G$3:$G$200,"Invoice")+SUMIFS('Orders & Payments'!$P$3:$P$200,'Orders & Payments'!$C$3:$C$200,$B43,'Orders & Payments'!$G$3:$G$200,"Delivery-Invoice")
A44: C-042 | B44: Stalagmite Connections | C44: 18130814 | D44: Mqabba | F44: Contractor | G44: 46074 | H44: =COUNTIF('Orders & Payments'!$C$3:$C$200,$B44) | I44: =SUMIFS('Orders & Payments'!$N$3:$N$200,'Orders & Payments'!$C$3:$C$200,$B44,'Orders & Payments'!$G$3:$G$200,"Quotation") | J44: =SUMIFS('Orders & Payments'!$N$3:$N$200,'Orders & Payments'!$C$3:$C$200,$B44,'Orders & Payments'!$G$3:$G$200,"Invoice")+SUMIFS('Orders & Payments'!$N$3:$N$200,'Orders & Payments'!$C$3:$C$200,$B44,'Orders & Payments'!$G$3:$G$200,"Delivery-Invoice") | K44: =SUMIFS('Orders & Payments'!$O$3:$O$200,'Orders & Payments'!$C$3:$C$200,$B44) | L44: =SUMIFS('Orders & Payments'!$P$3:$P$200,'Orders & Payments'!$C$3:$C$200,$B44,'Orders & Payments'!$G$3:$G$200,"Invoice")+SUMIFS('Orders & Payments'!$P$3:$P$200,'Orders & Payments'!$C$3:$C$200,$B44,'Orders & Payments'!$G$3:$G$200,"Delivery-Invoice")
A45: C-043 | B45: Blane | C45: — (confirm) | D45: Santa Lucia | F45: Private / TBC | G45: 46074 | H45: =COUNTIF('Orders & Payments'!$C$3:$C$200,$B45) | I45: =SUMIFS('Orders & Payments'!$N$3:$N$200,'Orders & Payments'!$C$3:$C$200,$B45,'Orders & Payments'!$G$3:$G$200,"Quotation") | J45: =SUMIFS('Orders & Payments'!$N$3:$N$200,'Orders & Payments'!$C$3:$C$200,$B45,'Orders & Payments'!$G$3:$G$200,"Invoice")+SUMIFS('Orders & Payments'!$N$3:$N$200,'Orders & Payments'!$C$3:$C$200,$B45,'Orders & Payments'!$G$3:$G$200,"Delivery-Invoice") | K45: =SUMIFS('Orders & Payments'!$O$3:$O$200,'Orders & Payments'!$C$3:$C$200,$B45) | L45: =SUMIFS('Orders & Payments'!$P$3:$P$200,'Orders & Payments'!$C$3:$C$200,$B45,'Orders & Payments'!$G$3:$G$200,"Invoice")+SUMIFS('Orders & Payments'!$P$3:$P$200,'Orders & Payments'!$C$3:$C$200,$B45,'Orders & Payments'!$G$3:$G$200,"Delivery-Invoice")
A46: C-044 | B46: JAA CO LTD | C46: MT2630-3713 | D46: Arzella Xitwija, Triq Gizi, Swieqi | F46: Commercial | G46: 46078 | H46: =COUNTIF('Orders & Payments'!$C$3:$C$200,$B46) | I46: =SUMIFS('Orders & Payments'!$N$3:$N$200,'Orders & Payments'!$C$3:$C$200,$B46,'Orders & Payments'!$G$3:$G$200,"Quotation") | J46: =SUMIFS('Orders & Payments'!$N$3:$N$200,'Orders & Payments'!$C$3:$C$200,$B46,'Orders & Payments'!$G$3:$G$200,"Invoice")+SUMIFS('Orders & Payments'!$N$3:$N$200,'Orders & Payments'!$C$3:$C$200,$B46,'Orders & Payments'!$G$3:$G$200,"Delivery-Invoice") | K46: =SUMIFS('Orders & Payments'!$O$3:$O$200,'Orders & Payments'!$C$3:$C$200,$B46) | L46: =SUMIFS('Orders & Payments'!$P$3:$P$200,'Orders & Payments'!$C$3:$C$200,$B46,'Orders & Payments'!$G$3:$G$200,"Invoice")+SUMIFS('Orders & Payments'!$P$3:$P$200,'Orders & Payments'!$C$3:$C$200,$B46,'Orders & Payments'!$G$3:$G$200,"Delivery-Invoice")
A47: C-045 | B47: Gordon Vella | C47: 16456105 | D47: Msida | F47: Private / TBC | G47: 46076 | H47: =COUNTIF('Orders & Payments'!$C$3:$C$200,$B47) | I47: =SUMIFS('Orders & Payments'!$N$3:$N$200,'Orders & Payments'!$C$3:$C$200,$B47,'Orders & Payments'!$G$3:$G$200,"Quotation") | J47: =SUMIFS('Orders & Payments'!$N$3:$N$200,'Orders & Payments'!$C$3:$C$200,$B47,'Orders & Payments'!$G$3:$G$200,"Invoice")+SUMIFS('Orders & Payments'!$N$3:$N$200,'Orders & Payments'!$C$3:$C$200,$B47,'Orders & Payments'!$G$3:$G$200,"Delivery-Invoice") | K47: =SUMIFS('Orders & Payments'!$O$3:$O$200,'Orders & Payments'!$C$3:$C$200,$B47) | L47: =SUMIFS('Orders & Payments'!$P$3:$P$200,'Orders & Payments'!$C$3:$C$200,$B47,'Orders & Payments'!$G$3:$G$200,"Invoice")+SUMIFS('Orders & Payments'!$P$3:$P$200,'Orders & Payments'!$C$3:$C$200,$B47,'Orders & Payments'!$G$3:$G$200,"Delivery-Invoice")
A48: C-046 | B48: BJORN | D48: Zabbar | F48: Private / TBC | G48: 46079 | H48: =COUNTIF('Orders & Payments'!$C$3:$C$200,$B48) | I48: =SUMIFS('Orders & Payments'!$N$3:$N$200,'Orders & Payments'!$C$3:$C$200,$B48,'Orders & Payments'!$G$3:$G$200,"Quotation") | J48: =SUMIFS('Orders & Payments'!$N$3:$N$200,'Orders & Payments'!$C$3:$C$200,$B48,'Orders & Payments'!$G$3:$G$200,"Invoice")+SUMIFS('Orders & Payments'!$N$3:$N$200,'Orders & Payments'!$C$3:$C$200,$B48,'Orders & Payments'!$G$3:$G$200,"Delivery-Invoice") | K48: =SUMIFS('Orders & Payments'!$O$3:$O$200,'Orders & Payments'!$C$3:$C$200,$B48) | L48: =SUMIFS('Orders & Payments'!$P$3:$P$200,'Orders & Payments'!$C$3:$C$200,$B48,'Orders & Payments'!$G$3:$G$200,"Invoice")+SUMIFS('Orders & Payments'!$P$3:$P$200,'Orders & Payments'!$C$3:$C$200,$B48,'Orders & Payments'!$G$3:$G$200,"Delivery-Invoice")
A49: C-047 | B49: MARSA | D49: Marsa | F49: Private / TBC | G49: 46074 | H49: =COUNTIF('Orders & Payments'!$C$3:$C$200,$B49) | I49: =SUMIFS('Orders & Payments'!$N$3:$N$200,'Orders & Payments'!$C$3:$C$200,$B49,'Orders & Payments'!$G$3:$G$200,"Quotation") | J49: =SUMIFS('Orders & Payments'!$N$3:$N$200,'Orders & Payments'!$C$3:$C$200,$B49,'Orders & Payments'!$G$3:$G$200,"Invoice")+SUMIFS('Orders & Payments'!$N$3:$N$200,'Orders & Payments'!$C$3:$C$200,$B49,'Orders & Payments'!$G$3:$G$200,"Delivery-Invoice") | K49: =SUMIFS('Orders & Payments'!$O$3:$O$200,'Orders & Payments'!$C$3:$C$200,$B49) | L49: =SUMIFS('Orders & Payments'!$P$3:$P$200,'Orders & Payments'!$C$3:$C$200,$B49,'Orders & Payments'!$G$3:$G$200,"Invoice")+SUMIFS('Orders & Payments'!$P$3:$P$200,'Orders & Payments'!$C$3:$C$200,$B49,'Orders & Payments'!$G$3:$G$200,"Delivery-Invoice")
A50: C-048 | B50: MOSTA | D50: Mosta | F50: Private / TBC | G50: 46083 | H50: =COUNTIF('Orders & Payments'!$C$3:$C$200,$B50) | I50: =SUMIFS('Orders & Payments'!$N$3:$N$200,'Orders & Payments'!$C$3:$C$200,$B50,'Orders & Payments'!$G$3:$G$200,"Quotation") | J50: =SUMIFS('Orders & Payments'!$N$3:$N$200,'Orders & Payments'!$C$3:$C$200,$B50,'Orders & Payments'!$G$3:$G$200,"Invoice")+SUMIFS('Orders & Payments'!$N$3:$N$200,'Orders & Payments'!$C$3:$C$200,$B50,'Orders & Payments'!$G$3:$G$200,"Delivery-Invoice") | K50: =SUMIFS('Orders & Payments'!$O$3:$O$200,'Orders & Payments'!$C$3:$C$200,$B50) | L50: =SUMIFS('Orders & Payments'!$P$3:$P$200,'Orders & Payments'!$C$3:$C$200,$B50,'Orders & Payments'!$G$3:$G$200,"Invoice")+SUMIFS('Orders & Payments'!$P$3:$P$200,'Orders & Payments'!$C$3:$C$200,$B50,'Orders & Payments'!$G$3:$G$200,"Delivery-Invoice") | M50: Supply & install Travertine Beige Atone (Mosta) — Inv 1000304 (supply) + Inv 1000305 (install). Client name not confirmed.
A51: C-049 | B51: Stefan Gajic | D51: Sliema | F51: Private / TBC | G51: 46087 | H51: =COUNTIF('Orders & Payments'!$C$3:$C$200,$B51) -> 0 | I51: =SUMIFS('Orders & Payments'!$N$3:$N$200,'Orders & Payments'!$C$3:$C$200,$B51,'Orders & Payments'!$G$3:$G$200,"Quotation") -> 0 | J51: =SUMIFS('Orders & Payments'!$N$3:$N$200,'Orders & Payments'!$C$3:$C$200,$B51,'Orders & Payments'!$G$3:$G$200,"Invoice")+SUMIFS('Orders & Payments'!$N$3:$N$200,'Orders & Payments'!$C$3:$C$200,$B51,'Orders & Payments'!$G$3:$G$200,"Delivery-Invoice") -> 0 | K51: =SUMIFS('Orders & Payments'!$O$3:$O$200,'Orders & Payments'!$C$3:$C$200,$B51) -> 0 | L51: =SUMIFS('Orders & Payments'!$P$3:$P$200,'Orders & Payments'!$C$3:$C$200,$B51,'Orders & Payments'!$G$3:$G$200,"Invoice")+SUMIFS('Orders & Payments'!$P$3:$P$200,'Orders & Payments'!$C$3:$C$200,$B51,'Orders & Payments'!$G$3:$G$200,"Delivery-Invoice") -> 0
A52: C-050 | B52: Target Developments Ltd | D52: Isabella Court, Flt Triq il-Mejjiesa, Manikata MLH 5134 | F52: Developer / Contractor | G52: 45901 | H52: =COUNTIF('Orders & Payments'!$C$3:$C$200,$B52) -> 0 | I52: =SUMIFS('Orders & Payments'!$N$3:$N$200,'Orders & Payments'!$C$3:$C$200,$B52,'Orders & Payments'!$G$3:$G$200,"Quotation") -> 0 | J52: =SUMIFS('Orders & Payments'!$N$3:$N$200,'Orders & Payments'!$C$3:$C$200,$B52,'Orders & Payments'!$G$3:$G$200,"Invoice")+SUMIFS('Orders & Payments'!$N$3:$N$200,'Orders & Payments'!$C$3:$C$200,$B52,'Orders & Payments'!$G$3:$G$200,"Delivery-Invoice") -> 0 | K52: =SUMIFS('Orders & Payments'!$O$3:$O$200,'Orders & Payments'!$C$3:$C$200,$B52) -> 0 | L52: =SUMIFS('Orders & Payments'!$P$3:$P$200,'Orders & Payments'!$C$3:$C$200,$B52,'Orders & Payments'!$G$3:$G$200,"Invoice")+SUMIFS('Orders & Payments'!$P$3:$P$200,'Orders & Payments'!$C$3:$C$200,$B52,'Orders & Payments'!$G$3:$G$200,"Delivery-Invoice") -> 0
A53: C-051 | B53: ST Projects Ltd | D53: 143 The Strand, Gzira | F53: Developer / Contractor | G53: 46090 | H53: =COUNTIF('Orders & Payments'!$C$3:$C$200,$B53) -> 0 | I53: =SUMIFS('Orders & Payments'!$N$3:$N$200,'Orders & Payments'!$C$3:$C$200,$B53,'Orders & Payments'!$G$3:$G$200,"Quotation") -> 0 | J53: =SUMIFS('Orders & Payments'!$N$3:$N$200,'Orders & Payments'!$C$3:$C$200,$B53,'Orders & Payments'!$G$3:$G$200,"Invoice")+SUMIFS('Orders & Payments'!$N$3:$N$200,'Orders & Payments'!$C$3:$C$200,$B53,'Orders & Payments'!$G$3:$G$200,"Delivery-Invoice") -> 0 | K53: =SUMIFS('Orders & Payments'!$O$3:$O$200,'Orders & Payments'!$C$3:$C$200,$B53) -> 0 | L53: =SUMIFS('Orders & Payments'!$P$3:$P$200,'Orders & Payments'!$C$3:$C$200,$B53,'Orders & Payments'!$G$3:$G$200,"Invoice")+SUMIFS('Orders & Payments'!$P$3:$P$200,'Orders & Payments'!$C$3:$C$200,$B53,'Orders & Payments'!$G$3:$G$200,"Delivery-Invoice") -> 0
H55: TOTALS → | I55: =SUM(I3:I54) -> 286888.31 | J55: =SUM(J3:J54) -> 139259.89 | K55: =SUM(K3:K54) -> 12372.58 | L55: =SUM(L3:L54) -> 126887.31

Sheet Measurement Pipeline
A1: MEASUREMENT → QUOTE → DEPOSIT → START
A2: Ref | B2: Date Logged | C2: Client / Site | D2: Contact | E2: Location | F2: Work Required | G2: Stage | H2: Measure Date | I2: Quote No. | J2: Quote Value | K2: Deposit Req. | L2: Deposit Paid? | M2: Lead Time (days) | N2: Target Start | O2: Notes | Q2: Default deposit % | R2: 0.3
A3: L-001 | B3: 45868 | C3: Qrendi (site) | E3: Qrendi | F3: Supply of marble slabs (limestone / travertine) | G3: Quote Sent — Awaiting Confirmation | I3: 229 | J3: 1910.42 | K3: =ROUND(J3*$R$2,2) -> 573.13 | L3: No | O3: Confirm client identity & VAT.
A4: L-002 | B4: 45917 | C4: Marsa – Hand-Crafted Job | E4: Marsa | F4: Hand-crafted marble designs, bullnose + polish | G4: Quote Sent — Awaiting Confirmation | I4: 239 | J4: 4448.6 | K4: =ROUND(J4*$R$2,2) -> 1334.58 | L4: No | O4: Doc labelled "MARSA".
A5: L-003 | B5: 45931 | C5: ROGER SATARIANO & SON LTD | E5: Mriehel | F5: Lava Black stairs & façade (31.6 sqm) | G5: Quote Sent — Awaiting Confirmation | I5: 243 | J5: 5109.4 | K5: =ROUND(J5*$R$2,2) -> 1532.82 | L5: No | O5: Linked to delivered extras (MD-016).
A6: L-004 | B6: 45959 | C6: ICI LIMITED | E6: Villa Fiorini | F6: Remove & replace marble sills | G6: Quote Sent — Awaiting Confirmation | I6: 259 | J6: 566.4 | K6: =ROUND(J6*$R$2,2) -> 169.92 | L6: No | O6: Existing client (ICI Ltd).
A7: L-005 | B7: 45959 | C7: Jhon Soler | E7: 15 Howard St, Sliema | F7: Supply & install 7 lifts cladding | G7: Quote Sent — Awaiting Confirmation | I7: 258 | J7: 2737.6 | K7: =ROUND(J7*$R$2,2) -> 821.28 | L7: No | O7: Per-floor delivery included.
A8: L-006 | B8: 45625 | C8: Luqa New Airport | E8: Luqa Airport | F8: Biege lime stone supply & install | G8: Quote Sent — Awaiting Confirmation | I8: 175 | J8: 7791.92 | K8: =ROUND(J8*$R$2,2) -> 2337.58 | L8: No | O8: Old quote — confirm if still open.
A9: L-007 | B9: 45976 | C9: Dario | E9: Marsa | F9: Supply of kitchen top — Quartz Gold | G9: Quote Sent — Awaiting Confirmation | I9: 264 | J9: 4012 | K9: =ROUND(J9*$R$2,2) -> 1203.6 | L9: No | O9: OPTION A (vs Q265 Calacatta). Client picks ONE.
A10: L-008 | B10: 45976 | C10: Dario | E10: Marsa | F10: Supply of kitchen top — Quartz Calacatta Gold | G10: Quote Sent — Awaiting Confirmation | I10: 265 | J10: 3569.5 | K10: =ROUND(J10*$R$2,2) -> 1070.85 | L10: No | O10: OPTION B (vs Q264 Quartz Gold). Client picks ONE.
A11: L-009 | B11: 45992 | C11: ROGER SATARIANO & SON LTD | E11: Pool & BBQ area | F11: Supply & install travertine — pool & barbeque area | G11: Quote Sent — Awaiting Confirmation | I11: 267 | J11: 4460.4 | K11: =ROUND(J11*$R$2,2) -> 1338.12 | L11: No | O11: Existing client. Separate from Mriehel & Ta Xbiex jobs.
A12: L-010 | B12: 45996 | C12: WE MALTA LTD | E12: Attard | F12: Supply & install Biege stone — stairs & skirting (Attard) | G12: Confirmed — Deposit Paid | I12: 272 | J12: 10612.92 | K12: =ROUND(J12*$R$2,2) -> 3183.88 | L12: Yes | O12: WON — invoiced as Delivery-Invoice 1000294 (see Orders MD-030). 40% deposit per doc.
A13: L-011 | B13: 45996 | C13: Purchase Order 1 (MARSA) | E13: Marsa | F13: Supply & install Crema Galala — stairs, landing & entrance (65.6 sqm) | G13: Quote Sent — Awaiting Confirmation | I13: 271 | J13: 8184.24 | K13: =ROUND(J13*$R$2,2) -> 2455.27 | L13: No | O13: Client labelled "PURCHASE ORDER 1" — identify.
A14: L-012 | B14: 45996 | C14: WE MALTA LTD | E14: Birkirkara | F14: Supply & install Biege stone — internal/external stairs & skirting (Birkirkara) | G14: Confirmed — Deposit Paid | I14: 273 | J14: 10105.99 | K14: =ROUND(J14*$R$2,2) -> 3031.8 | L14: Yes | O14: WON — invoiced as Delivery-Invoice 1000295 (see Orders MD-032). 40% deposit per doc.
... A32: L-030 | B32: 46057 | C32: Purchase Order 1 (MARSA) | E32: Marsa | F32: Supply & install Prestige Grey & Bianco Carrera staircases + sills | G32: Quote Sent — Awaiting Confirmation | I32: 300 | J32: 42441.06 | K32: =ROUND(J32*$R$2,2) -> 12732.32 | L32: No | O32: Client "PURCHASE ORDER 1" — identify. Largest open quote.
A33: L-031 | B33: 46060 | C33: Purchase Order 1 (MARSA) | E33: Marsa | F33: Supply & install Calacatta Viola sink & backsplash | G33: Quote Sent — Awaiting Confirmation | I33: 301 | J33: 4017.9 | K33: =IF(J33="","",ROUND(J33*$R$2,2)) -> 1205.37 | L33: No | O33: Identify client. Install €200–300.
A34: L-032 | B34: 46060 | C34: ICI LIMITED | E34: Attard | F34: Supply of Travertine crosscut sills & stairs | G34: Quote Sent — Awaiting Confirmation | I34: 302 | J34: 4285.35 | K34: =IF(J34="","",ROUND(J34*$R$2,2)) -> 1285.61 | L34: No | O34: VAT MT17813220. MEASURED — cut list. F1 sills: 152.5×35, 4.55×21, 1.05×21 ×2, 1.115×26, 79.5×12, 1.09×26, 62×12, 98×26, 2.42×21, 1.12×21, 1.10×21. F2 sills: 1.51×26, 4.295×21, 1.02×21 ×2, 1.135×26, 80×12, 1.09×26, 99.5×26, 62×12, 1.09×26, 2.03×21, 1.01×21 ×2. F3 sills: 150.5×26, 4.29×21, 1.02×21 ×2, 1.15×26, 89×12, 1.09×26, 1.10×26, 62×12, 99.5×12, 2.03×21, 1.02×21 ×2. Penthouse: 3.955×27, 48.5×27, 6.75×27, 4.28×27, 49×27, 1.15×26, 1.10×26, 60×12, 80×12, 4.30×27, 3.75×27 ×2, 1.30×27, 1.51×21. Stairs: 94×1.50 ×4, 1.50×1.10 ×8, 1.15×2.20 ×4. Entrance: 1.15×2.20, 94×50 ×6, 2.10×3.50, 3.10×1.50. Outdoor: 2.70×1.50. (m unless cm)
A35: L-033 | B35: 46060 | C35: VGP PROPERTY INVESTMENT COMPANY LIMITED | E35: Floriana | F35: Supply & install Bianco Carrera sills | G35: Invoiced — Delivery-Invoice 1000290 | I35: 303 | J35: 687.35 | K35: =IF(J35="","",ROUND(J35*$R$2,2)) -> 206.21 | L35: No | O35: VAT 28035504. Bianco sills + install + delivery, Triq Antonio Aguis.
A36: L-034 | B36: 46060 | C36: VGP PROPERTY INVESTMENT COMPANY LIMITED | E36: Floriana | F36: Supply & install sills & stairs, F-1 to roof | G36: Quote Sent — Awaiting Confirmation | I36: 304 | J36: 5422.75 | K36: =IF(J36="","",ROUND(J36*$R$2,2)) -> 1626.83 | L36: No | O36: VAT 28035504. MEASURED — cut list (F-1 to roof). F-1 sills: 1.07×27, 1.10×27, 90×42, 91×41, 2.70×20 ×2, 70×20 ×2; F-1 stairs: 2.50×1.11, 15×1.11 ×6. F-2 sills: 4.53×25, 4.53×21, 91×36, 91×35.5, 91×35.4, 3.50×26, 4.40×22, 92×36, 91×36, 2.24×26 ×2, 1.42×26; F-2 stairs: 1.85×1.11, 1.11×15 ×5, 1.11×23 ×3. F-3 sills: 2.20×26 ×2, 90×40 ×2, 91×40 ×2, 92×40, 1.42×26; F-3 stairs: 1.33×1.11 ×2, 1.11×15 ×2, 1.11×40, 1.11×50. Roof sills: 75×26 ×2, 80.5×26, 12.55×26, 8.75×26, 2.90×18, 1.63×18, 2.00×26 ×2, 1.40×26. (m unless cm)
A37: L-035 | B37: 46055 | C37: Joesph Guzieppe Callus | E37: Mosta | F37: Supply & install Dino brushed stairs + sills | G37: Quote Sent — Awaiting Confirmation | I37: 292 | J37: 7149.62 | K37: =IF(J37="","",ROUND(J37*$R$2,2)) -> 2144.89 | L37: No | O37: No VAT on doc — confirm.
A38: L-036 | B38: 46065 | C38: Maria | E38: Mosta | F38: Supply & install Taj Mahal kitchen top + splashback + island | G38: Quote Sent — Awaiting Confirmation | I38: 305 | J38: 7398.6 | K38: =IF(J38="","",ROUND(J38*$R$2,2)) -> 2219.58 | L38: No | O38: VAT 26849627, Il-Maxtura, Mosta.
A39: L-037 | B39: 46065 | C39: Itiana | E39: Marsaskala | F39: Supply & install travertine, multi-floor | G39: Invoiced — Delivery-Invoice 1000296 | I39: 306 | J39: 9196.92 | K39: =IF(J39="","",ROUND(J39*$R$2,2)) -> 2759.08 | L39: No | O39: No VAT on doc — confirm.
A40: L-038 | B40: 46067 | C40: MSIDA | E40: Msida | F40: Supply & Install Bianco Carrara Sills (Roof Sills, Round Sills, Level 1+2+3+4, Install) | G40: Invoiced — Delivery-Invoice 1000303 (partial, deposit paid) | I40: 309 | J40: 17941.43 | K40: =IF(J40="","",ROUND(J40*$R$2,2)) | L40: No | O40: Open quote — add to Measurement Pipeline
A41: L-039 | B41: 46067 | C41: GUDJA | E41: Gudja | F41: Supply & Install Staircase Beige (Stairs & Skirting) | G41: Quote Sent — Awaiting Confirmation | I41: 310 | J41: 11016.48 | K41: =IF(J41="","",ROUND(J41*$R$2,2)) | L41: No | O41: Open quote — add to Measurement Pipeline
A42: L-040 | B42: 46074 | C42: Blane | E42: Santa Lucia | F42: Supply of Crema Marfil Sills + Delivery | G42: Quote Sent — Awaiting Confirmation | I42: 317 | J42: 551.65 | K42: =IF(J42="","",ROUND(J42*$R$2,2)) | L42: No | O42: Open quote — Santa Lucia
A43: L-041 | B43: 46074 | C43: MARSA | E43: Marsa | F43: Supply of Crema Galala Sills + Delivery | G43: Quote Sent — Awaiting Confirmation | I43: 318 | J43: 457.25 | K43: =IF(J43="","",ROUND(J43*$R$2,2)) | L43: No | O43: Client name not on document — confirm client name
A44: L-042 | B44: 46076 | C44: Gordon Vella | E44: Msida | F44: Supply of Light Travertine Sills (Sills, Stairs, Entrance) | G44: Quote Sent — Awaiting Confirmation | I44: 323 | J44: 24763.72 | K44: =IF(J44="","",ROUND(J44*$R$2,2)) | L44: No | O44: Open quote — add to Measurement Pipeline
... A46: L-044 | B46: 46079 | C46: BJORN | E46: Zabbar | F46: Supply & Install Quarzite & Crema Marfil Marble (back light included with installation) | G46: Quote Sent — Awaiting Confirmation | I46: 325 | J46: 7882.4 | K46: =IF(J46="","",ROUND(J46*$R$2,2)) | L46: No | O46: Open quote — back light included with installation; add to Measurement Pipeline
K47: =IF(J47="","",ROUND(J47*$R$2,2))
K48: =IF(J48="","",ROUND(J48*$R$2,2))
K49: =IF(J49="","",ROUND(J49*$R$2,2))
K50: =IF(J50="","",ROUND(J50*$R$2,2))
K51: =IF(J51="","",ROUND(J51*$R$2,2))
K52: =IF(J52="","",ROUND(J52*$R$2,2))
K53: =IF(J53="","",ROUND(J53*$R$2,2))
K54: =IF(J54="","",ROUND(J54*$R$2,2))
K55: =IF(J55="","",ROUND(J55*$R$2,2))
K56: =IF(J56="","",ROUND(J56*$R$2,2))
K57: =IF(J57="","",ROUND(J57*$R$2,2))
K58: =IF(J58="","",ROUND(J58*$R$2,2))
... K62: =IF(J62="","",ROUND(J62*$R$2,2))

Sheet Cutting Log
A1: CUTTING LOG — what the machine cutter cut each day
A2: Date | B2: Cutter | C2: Order ID | D2: Client / Site | E2: Invoice / Quote | F2: Material | G2: Pieces / Sizes Cut | H2: Sqm Cut | I2: Lm Cut | J2: Chamfer Done? | K2: Chamfer By | L2: Status | M2: Notes
A3: 45966 | B3: Cutter (rename) | C3: MD-017 | D3: PROJECT TECHNIK LTD | E3: 1000255 | F3: Trista Grey | G3: 27 sqm slabs cut to size | H3: 27 | J3: Yes | K3: Chamfer (rename) | L3: Completed | M3: EXAMPLE — Trista Grey order delivered
A4: 45967 | B4: Cutter (rename) | C4: MD-019 | D4: Lee | E4: 1000256 | F4: Biege Travertine | G4: Sills: 90.5×26, 66×26, 91×26, 1m×26, 1m×25, 90×32, 84×10, 54×10, 88×21, 86×21 (11 pcs) | H4: 2.5 | J4: Yes | K4: Chamfer (rename) | L4: Ready for Delivery | M4: EXAMPLE — travertine sills
A5: 45974 | B5: Cutter (rename) | C5: MD-020 | D5: STEPHEN FARRUGIA | E5: 1000258 | F5: Marble | G5: Install pieces — Santa Venera | J5: Yes | K5: Chamfer (rename) | L5: In Progress | M5: EXAMPLE — supply & install balance

Sheet Daily Work Log
A1: DAILY WORK LOG — what every worker did today
A2: Date | B2: Worker | C2: Role | D2: Activity | E2: Order ID | F2: Client / Site | G2: Material | H2: Details (what they did) | I2: Qty (pcs) | J2: Sqm / Lm | K2: Hours | L2: Status | M2: Notes
A3: 45967 | B3: Cutter (rename) | C3: Machine Cutter | D3: Cutting | E3: MD-019 | F3: Lee | G3: Biege Travertine | H3: Cut 11 travertine sills to required sizes | I3: 11 | K3: 5 | L3: Completed | M3: EXAMPLE
A4: 45967 | B4: Chamfer (rename) | C4: Chamfer | D4: Chamfering | E4: MD-019 | F4: Lee | G4: Biege Travertine | H4: Chamfered / edged 11 sills | I4: 11 | K4: 3 | L4: Completed | M4: EXAMPLE
A5: 45967 | B5: Helper (rename) | C5: Helper | D5: Factory Help | E5: MD-019 | F5: Lee | H5: Moved slabs to cutter, cleaned, stacked finished pieces | K5: 6 | L5: Completed | M5: EXAMPLE
A6: 45967 | B6: Driver (rename) | C6: Driver | D6: Delivery | E6: MD-019 | F6: Lee (Marsa) | H6: Delivered finished sills to site + unloaded | K6: 2 | L6: Completed | M6: EXAMPLE
A7: 45967 | B7: Driver (rename) | C7: Driver | D7: Factory Help | H7: Helped load van, moved offcuts, tidied yard | K7: 3 | L7: Completed | M7: EXAMPLE
A8: 45966 | B8: Cutter (rename) | C8: Machine Cutter | D8: Cutting | E8: MD-017 | F8: PROJECT TECHNIK LTD | G8: Trista Grey | H8: Cut 27 sqm Trista Grey to size | J8: 27 | K8: 6 | L8: Completed | M8: EXAMPLE

Sheet Attendance
A1: WORKER ATTENDANCE — arrival times, factory & outside
A2: Date | B2: Worker | C2: Role | D2: Work Location | E2: Time In | F2: Time Out | G2: Hours | H2: Status | I2: Notes
A3: 45967 | B3: Cutter (rename) | C3: Machine Cutter | D3: Factory | E3: 0.29166667 | F3: 0.6875 | G3: =IF(OR(E3="",F3=""),"",(F3-E3)*24) -> 9.5 | H3: Present | I3: —
A4: 45967 | B4: Chamfer (rename) | C4: Chamfer | D4: Factory | E4: 0.30208333 | F4: 0.6875 | G4: =IF(OR(E4="",F4=""),"",(F4-E4)*24) -> 9.25 | H4: Late | I4: In 15 min late
A5: 45967 | B5: Helper (rename) | C5: Helper | D5: Factory | E5: 0.29166667 | F5: 0.66666667 | G5: =IF(OR(E5="",F5=""),"",(F5-E5)*24) -> 9 | H5: Present | I5: —
A6: 45967 | B6: Driver (rename) | C6: Driver | D6: Outside / Site | E6: 0.28125 | F6: 0.70833333 | G6: =IF(OR(E6="",F6=""),"",(F6-E6)*24) -> 10.25 | H6: Present | I6: Deliveries Marsa + Qormi
A7: 45967 | B7: Installer (rename) | C7: Installer | D7: Outside / Site | E7: 0.3125 | F7: 0.6875 | G7: =IF(OR(E7="",F7=""),"",(F7-E7)*24) -> 9 | H7: Present | I7: On site — Zebbug flats
G8: =IF(OR(E8="",F8=""),"",(F8-E8)*24)
G9: =IF(OR(E9="",F9=""),"",(F9-E9)*24)
G10: =IF(OR(E10="",F10=""),"",(F10-E10)*24)
G11: =IF(OR(E11="",F11=""),"",(F11-E11)*24)
G12: =IF(OR(E12="",F12=""),"",(F12-E12)*24)
G13: =IF(OR(E13="",F13=""),"",(F13-E13)*24)
G14: =IF(OR(E14="",F14=""),"",(F14-E14)*24)
G15: =IF(OR(E15="",F15=""),"",(F15-E15)*24)
G16: =IF(OR(E16="",F16=""),"",(F16-E16)*24)
G17: =IF(OR(E17="",F17=""),"",(F17-E17)*24)
G18: =IF(OR(E18="",F18=""),"",(F18-E18)*24)
G19: =IF(OR(E19="",F19=""),"",(F19-E19)*24)
... G400: =IF(OR(E400="",F400=""),"",(F400-E400)*24)

Sheet Workers
A1: WORKERS — team roster
A2: Worker ID | B2: Name | C2: Role | D2: Base | E2: Phone | F2: Rate | G2: Rate Type | H2: Start Date | I2: Status | J2: Notes
A3: W-001 | B3: Cutter (rename) | C3: Machine Cutter | D3: Factory | G3: Daily | I3: Active | J3: Operates the cutting machine.
A4: W-002 | B4: Chamfer (rename) | C4: Chamfer / Edging | D4: Factory | G4: Daily | I4: Active | J4: Chamfering / bullnose / edge finishing.
A5: W-003 | B5: Helper (rename) | C5: Helper | D5: Factory | G5: Daily | I5: Active | J5: Moves slabs, assists cutter, yard work.
A6: W-004 | B6: Driver (rename) | C6: Driver / Delivery | D6: Both | G6: Daily | I6: Active | J6: Deliveries + helps in factory between runs.
A7: W-005 | B7: Installer (rename) | C7: Installer | D7: Outside / Site | G7: Daily | I7: Active | J7: Fits sills, stairs, cladding on site.
A8: W-006 | B8: Mason (rename) | C8: Mason / Fixer | D8: Outside / Site | G8: Daily | I8: Active | J8: Leveling, fixing, finishing on site.

Sheet Guide
A1: HOW TO USE THIS WORKBOOK
B4: TAB | C4: WHAT IT IS FOR
B5: Dashboard | C5: Live snapshot — money invoiced, money received, money still owed, and value of quotes not yet confirmed. Updates by itself.
B6: Orders & Payments | C6: The heart of the system. One row per quote, invoice or delivery note. Fill the YELLOW cells (Deposit/Paid, Lead Time, Delivery date). "Pending" works out Total − Paid automatically. As you upload more invoices, add a new row at the bottom.
B7: Client Directory | C7: Every client pulled from your documents. Quoted / Invoiced / Received / Outstanding totals add up automatically per client from the Orders tab. Just fill in their phone/email.
B8: Measurement Pipeline | C8: Your sales funnel: who needs a site measurement, who has a quote, who paid a deposit, when work can start. Open quotes are pre-loaded. Suggested deposit = Quote × the % in the box (top-right, default 30%).
B9: Cutting Log | C9: Daily record of what the cutting-machine man cut — which order, sizes, sqm, whether it was chamfered and by whom, and whether it is ready to deliver.
B10: Daily Work Log | C10: What EVERY worker did each day — cutter, chamfer, helper, driver (deliveries + factory help) and installers. One line per task, linked to an Order ID.
B11: Attendance | C11: Clock-in / clock-out with arrival time. "Work Location" splits factory vs outside staff. Hours calculate automatically from the times.
B12: Workers | C12: Team roster. Replace "(rename)" with real names.
B14: COLOURS | C14: MEANING
B15: Yellow cell | C15: Type your information here.
B16: Green status | C16: Done / Paid / Confirmed.
... B26: 5. Delivery / install | C26: Supply-only paid on delivery; supply & install paid on completion. Log payment in Orders → Pending drops to zero.

Sheet Price Book
A1: MD Marble — Client Price Book
A2: Client | B2: Doc Ref | C2: Date | D2: Site | E2: Material / Item | F2: Unit | G2: Qty | H2: Unit Price (€) | I2: Item Total (€) | J2: Work Type | K2: Notes
A3: BJORN | B3: Zabbar
A4: BJORN | B4: Q324 | C4: 46079 | D4: Zabbar | E4: Nero Assaluto | F4: unit | G4: 1 | H4: 1520 | I4: 1520 | J4: Supply & Install
A5: BJORN | B5: Q324 | C5: 46079 | D5: Zabbar | E5: Bianco Marble | F5: unit | G5: 1 | H5: 1680 | I5: 1680 | J5: Supply & Install
A6: BJORN | B6: Q324 | C6: 46079 | D6: Zabbar | E6: Installation | F6: unit | G6: 1 | H6: 1100 | I6: 1100 | J6: Installation
A7: BJORN | B7: Q325 | C7: 46079 | D7: Zabbar | E7: Crema Marfil | F7: unit | G7: 1 | H7: 960 | I7: 960 | J7: Supply & Install
A8: BJORN | B8: Q325 | C8: 46079 | D8: Zabbar | E8: Quarzite | F8: unit | G8: 1 | H8: 4440 | I8: 4440 | J8: Supply & Install
A9: BJORN | B9: Q325 | C9: 46079 | D9: Zabbar | E9: Installation (incl. back light) | F9: unit | G9: 1 | H9: 1280 | I9: 1280 | J9: Installation | K9: Back light included
A10: Blane | B10: Santa Lucia
A11: Blane | B11: Q317 | C11: 46074 | D11: Santa Lucia | E11: Crema Marfil Sills | F11: unit | G11: 1 | H11: 427.5 | I11: 427.5 | J11: Supply Only
A12: Blane | B12: Q317 | C12: 46074 | D12: Santa Lucia | E12: Delivery | F12: unit | G12: 1 | H12: 40 | I12: 40 | J12: Delivery
A13: Cassar Ship Repair Ltd | B13: Marsa
A14: Cassar Ship Repair Ltd | B14: Inv400215 | C14: 46070 | D14: Marsa | E14: Marble Sills | F14: unit | G14: 1 | H14: 90 | I14: 90 | J14: Supply Only
A15: Gordon Vella | B15: Msida
A16: Gordon Vella | B16: Q323 | C16: 46076 | D16: Msida | E16: Light Travertine Sills | F16: SQM | G16: 35 | H16: 89 | I16: 3115 | J16: Supply Only
A17: Gordon Vella | B17: Q323 | C17: 46076 | D17: Msida | E17: Light Travertine Stairs | F17: SQM | G17: 165 | H17: 89 | I17: 14685 | J17: Supply Only
A18: Gordon Vella | B18: Q323 | C18: 46076 | D18: Msida | E18: Light Travertine Entrance | F18: SQM | G18: 35.8 | H18: 89 | I18: 3186.2 | J18: Supply Only
A19: GUDJA | B19: Gudja
A20: GUDJA | B20: Q310 | C20: 46067 | D20: Gudja | E20: Supply of Stairs and Skirting (Beige) | F20: SQM | G20: 77.8 | H20: 70 | I20: 5446 | J20: Supply & Install
A21: GUDJA | B21: Q310 | C21: 46067 | D21: Gudja | E21: Installation of Stairs and Skirting | F21: unit | G21: 1 | H21: 3890 | I21: 3890 | J21: Installation
A22: ITIANA | B22: Marsaskala
A23: ITIANA | B23: 1000296/Q306 | C23: 46067 | D23: Marsaskala | E23: Travertine (1st-2nd-3rd Floor) | F23: SQM | G23: 14.8 | H23: 85 | I23: 1258 | J23: Supply & Install
A24: ITIANA | B24: 1000296/Q306 | C24: 46067 | D24: Marsaskala | E24: Travertine (4th Floor) | F24: SQM | G24: 13.8 | H24: 85 | I24: 1173 | J24: Supply & Install
A25: ITIANA | B25: 1000296/Q306 | C25: 46067 | D25: Marsaskala | E25: Travertine (5th Floor) | F25: SQM | G25: 13.3 | H25: 85 | I25: 1130.5 | J25: Supply & Install
A26: ITIANA | B26: 1000296/Q306 | C26: 46067 | D26: Marsaskala | E26: Travertine (Ground Floor) | F26: SQM | G26: 3.2 | H26: 85 | I26: 272 | J26: Supply & Install
A27: ITIANA | B27: 1000296/Q306 | C27: 46067 | D27: Marsaskala | E27: Travertine (Back Yard) | F27: SQM | G27: 8.3 | H27: 85 | I27: 705.5 | J27: Supply & Install
A28: ITIANA | B28: 1000296/Q306 | C28: 46067 | D28: Marsaskala | E28: Installation | F28: Lm | G28: 217 | H28: 15 | I28: 3255 | J28: Installation
A29: JAA CO LTD | B29: Swieqi
A30: JAA CO LTD | B30: 1000302 | C30: 46078 | D30: Swieqi | E30: Supply of Marble Marsaskala | F30: unit | G30: 1 | H30: 11533.18 | I30: 11533.18 | J30: Supply Only
A31: Malta International Airport PLC | B31: Luqa
A32: Malta International Airport PLC | B32: 1000299/Q299 | C32: 46071 | D32: Luqa | E32: Lime Stone Sills 10m×14cm | F32: unit | G32: 1 | H32: 255 | I32: 255 | J32: Supply Only
A33: Malta International Airport PLC | B33: 1000299/Q299 | C33: 46071 | D33: Luqa | E33: Delivery | F33: unit | G33: 1 | H33: 30 | I33: 30 | J33: Delivery
A34: MARSA | B34: Marsa
A35: MARSA | B35: Q318 | C35: 46074 | D35: Marsa | E35: Crema Galala Sills | F35: unit | G35: 1 | H35: 337.5 | I35: 337.5 | J35: Supply Only | K35: Client name not confirmed on doc
A36: MARSA | B36: Q318 | C36: 46074 | D36: Marsa | E36: Delivery | F36: unit | G36: 1 | H36: 50 | I36: 50 | J36: Delivery
A37: May Grech | B37: Marsaxlokk
A38: May Grech | B38: 1000298 | C38: 46070 | D38: Marsaxlokk | E38: Marble (Penthouse) | F38: unit | G38: 1 | H38: 370 | I38: 370 | J38: Supply Only
A39: MSIDA | B39: Msida
A40: MSIDA | B40: Inv1000303/Q309 | C40: 46067 | D40: Msida | E40: Bianco Carrara Roof Sills | F40: SQM | G40: 23.3 | H40: 80 | I40: 1864 | J40: Supply & Install
A41: MSIDA | B41: Inv1000303/Q309 | C41: 46067 | D41: Msida | F41: SQM | G41: 44.85 | H41: 80 | I41: 3588 | J41: Supply & Install | E41: Bianco Carrara Sills Level 1+2+3+4
A42: MSIDA | B42: Q309 | C42: 46067 | D42: Msida | F42: SQM | G42: 0 | H42: 0 | I42: 0 | J42: Supply & Install | E42: [REMOVED] Old Sills Level 1+2+3+4 entry — revised, see Inv 1000303 | K42: revised — see Inv 1000303
A43: MSIDA | B43: Q309 | C43: 46067 | D43: Msida | F43: unit | G43: 0 | H43: 0 | I43: 0 | J43: Installation | E43: [REMOVED] Old Installation (all sills) entry — revised, see Inv 1000303 | K43: revised — see Inv 1000303
A44: Stalagmite Connections | B44: Mqabba
A45: Stalagmite Connections | B45: Inv400217 | C45: 46074 | D45: Mqabba | E45: Marble Stair Fgura Etienne (deposit) | F45: unit | G45: 1 | H45: 423.73 | I45: 423.73 | J45: Supply Only | K45: Deposit invoice — full order TBC
A46: VGP Property Investment Company Limited | B46: Naxxar
A47: VGP Property Investment Company Limited | B47: 1000290/Q303 | C47: 46065 | D47: Naxxar | E47: Bianco Carrera Sills | F47: unit | G47: 1 | H47: 349.5 | I47: 349.5 | J47: Supply & Install
A48: VGP Property Investment Company Limited | B48: 1000290/Q303 | C48: 46065 | D48: Naxxar | E48: Installation | F48: unit | G48: 1 | H48: 198 | I48: 198 | J48: Installation
A49: VGP Property Investment Company Limited | B49: 1000290/Q303 | C49: 46065 | D49: Naxxar | E49: Delivery | F49: unit | G49: 1 | H49: 35 | I49: 35 | J49: Delivery
A50: VGP Property Investment Company Limited | B50: 1000290/Q303 | C50: 46065 | D50: Naxxar | E50: Extra Piece 2.40×25cm | F50: unit | G50: 1 | H50: 70 | I50: 70 | J50: Supply & Install
A51: MOSTA (Mosta) | B51: Mosta
A52: MOSTA (Mosta) | B52: Inv1000304 | C52: 46083 | D52: Mosta | E52: Travertine Beige Atone — Main Stairs | F52: SQM | G52: 279 | H52: 68 | I52: 18972 | J52: Supply Only
A53: MOSTA (Mosta) | B53: Inv1000304 | C53: 46083 | D53: Mosta | E53: Travertine Beige Atone — Sills | F53: SQM | G53: 38 | H53: 68 | I53: 2584 | J53: Supply Only
A54: MOSTA (Mosta) | B54: Inv1000304 | C54: 46083 | D54: Mosta | E54: Travertine Beige Atone — Second Stair Case | F54: SQM | G54: 162 | H54: 68 | I54: 11016 | J54: Supply Only
A55: MOSTA (Mosta) | B55: Inv1000304 | C55: 46083 | D55: Mosta | E55: Facade Travertine (40x60cm) 1.2mm | F55: SQM | G55: 104 | H55: 40 | I55: 4160 | J55: Supply Only
A56: MOSTA (Mosta) | B56: Inv1000305 | C56: 46083 | D56: Mosta | E56: Installation — Stairs | F56: SQM | G56: 441 | H56: 40 | I56: 17640 | J56: Installation Only | K56: Installation invoice for same Mosta job as Inv 1000304; client name not confirmed
A57: MOSTA (Mosta) | B57: Inv1000305 | C57: 46083 | D57: Mosta | E57: Installation — Sills | F57: Lm | G57: 114 | H57: 15 | I57: 1710 | J57: Installation Only | K57: Installation invoice for same Mosta job as Inv 1000304; client name not confirmed
A58: MOSTA (Mosta) | B58: Inv1000305 | C58: 46083 | D58: Mosta | E58: Installation — Facade | F58: SQM | G58: 105 | H58: 35 | I58: 3675 | J58: Installation Only | K58: Installation invoice for same Mosta job as Inv 1000304; client name not confirmed
A59: Stefan Gajic (Sliema) | B59: Sliema
A60: Stefan Gajic | B60: 1000306 | C60: 46087 | D60: Sliema | E60: Supply of Bianco Carrera Tables (80×80cm) | F60: unit | G60: 1 | H60: 980 | I60: 980 | J60: Supply Only | K60: 4 tables, 1.90×80cm + 10cm Bastuon 45° cut
A61: Stefan Gajic | B61: 1000306 | C61: 46087 | D61: Sliema | E61: Delivery | F61: unit | G61: 1 | H61: 50 | I61: 50 | J61: Delivery
A62: ICI LIMITED (Birkirkara) | B62: Birkirkara
A63: ICI LIMITED | B63: 1000307/Q302 | C63: 46087 | D63: Birkirkara | E63: Travertine Crosscut Sills 18–27cm | F63: Lm | G63: 81.37 | H63: 23 | I63: 1871.51 | J63: Supply & Install
A64: ICI LIMITED | B64: 1000307/Q302 | C64: 46087 | D64: Birkirkara | E64: Travertine Crosscut Sills ≤17cm | F64: Lm | G64: 7.15 | H64: 19 | I64: 135.85 | J64: Supply & Install
A65: ICI LIMITED | B65: 1000307/Q302 | C65: 46087 | D65: Birkirkara | E65: Travertine Crosscut Sills >33cm | F65: SQM | G65: 0.77 | H65: 90 | I65: 69.3 | J65: Supply & Install
A66: ICI LIMITED | B66: 1000307/Q302 | C66: 46087 | D66: Birkirkara | E66: Installation of Sills | F66: unit | G66: 1 | H66: 1555 | I66: 1555 | J66: Installation
A67: Target Developments Ltd (Manikata) | B67: Manikata
A68: Target Developments Ltd | B68: 1000231 | C68: 45901 | D68: Manikata | E68: Travertine — Gzira Penthouse (remaining 30% payment) | F68: unit | G68: 1 | H68: 3786 | I68: 3786 | J68: Supply & Install | K68: Partial — €1,890.48 still pending
A69: ST Projects Ltd (Gzira) | B69: Gzira
A70: ST Projects Ltd | B70: 1000309 | C70: 46090 | D70: Gzira | E70: Galal Marble Sills — Up to 30cm width | F70: Lm | G70: 246.21 | H70: 16 | I70: 3939.36 | J70: Supply Only
A71: ST Projects Ltd | B71: 1000309 | C71: 46090 | D71: Gzira | E71: Galal Marble Sills — 32cm width | F71: Lm | G71: 14.8 | H71: 17.2 | I71: 254.56 | J71: Supply Only
A72: ST Projects Ltd | B72: 1000309 | C72: 46090 | D72: Gzira | E72: Galal Marble Sills — 43cm width | F72: Lm | G72: 15 | H72: 23.8 | I72: 357 | J72: Supply Only
